{
  "see books" : {
    "transaction" : "see books",
    "sampleCount" : 54,
    "errorCount" : 5,
    "errorPct" : 9.259259,
    "meanResTime" : 3008.9814814814804,
    "medianResTime" : 2908.5,
    "minResTime" : 2432.0,
    "maxResTime" : 3941.0,
    "pct1ResTime" : 3461.5,
    "pct2ResTime" : 3657.0,
    "pct3ResTime" : 3941.0,
    "throughput" : 0.24446114425923743,
    "receivedKBytesPerSec" : 418.0221772447984,
    "sentKBytesPerSec" : 3.0384562632416454
  },
  "https://demoqa.com/Account/v1/User/dce91940-7746-4f23-b7db-cf03bbe12f06" : {
    "transaction" : "https://demoqa.com/Account/v1/User/dce91940-7746-4f23-b7db-cf03bbe12f06",
    "sampleCount" : 1,
    "errorCount" : 0,
    "errorPct" : 0.0,
    "meanResTime" : 179.0,
    "medianResTime" : 179.0,
    "minResTime" : 179.0,
    "maxResTime" : 179.0,
    "pct1ResTime" : 179.0,
    "pct2ResTime" : 179.0,
    "pct3ResTime" : 179.0,
    "throughput" : 5.58659217877095,
    "receivedKBytesPerSec" : 1.783999650837989,
    "sentKBytesPerSec" : 3.3334060754189947
  },
  "https://demoqa.com/BookStore/v1/Books?UserId=ced950c7-0116-499e-b920-1a67e8fa6c0b" : {
    "transaction" : "https://demoqa.com/BookStore/v1/Books?UserId=ced950c7-0116-499e-b920-1a67e8fa6c0b",
    "sampleCount" : 1,
    "errorCount" : 0,
    "errorPct" : 0.0,
    "meanResTime" : 273.0,
    "medianResTime" : 273.0,
    "minResTime" : 273.0,
    "maxResTime" : 273.0,
    "pct1ResTime" : 273.0,
    "pct2ResTime" : 273.0,
    "pct3ResTime" : 273.0,
    "throughput" : 3.663003663003663,
    "receivedKBytesPerSec" : 0.6617731227106226,
    "sentKBytesPerSec" : 2.525469322344322
  },
  "https://demoqa.com/books?book=9781449337711-5" : {
    "transaction" : "https://demoqa.com/books?book=9781449337711-5",
    "sampleCount" : 17,
    "errorCount" : 0,
    "errorPct" : 0.0,
    "meanResTime" : 51.411764705882355,
    "medianResTime" : 46.0,
    "minResTime" : 20.0,
    "maxResTime" : 111.0,
    "pct1ResTime" : 82.99999999999997,
    "pct2ResTime" : 111.0,
    "pct3ResTime" : 111.0,
    "throughput" : 0.09034863945578231,
    "receivedKBytesPerSec" : 4.337772706738946,
    "sentKBytesPerSec" : 0.04850634101296769
  },
  "deleteBook" : {
    "transaction" : "deleteBook",
    "sampleCount" : 14,
    "errorCount" : 0,
    "errorPct" : 0.0,
    "meanResTime" : 273.57142857142856,
    "medianResTime" : 264.5,
    "minResTime" : 240.0,
    "maxResTime" : 373.0,
    "pct1ResTime" : 357.5,
    "pct2ResTime" : 373.0,
    "pct3ResTime" : 373.0,
    "throughput" : 0.08908402532531577,
    "receivedKBytesPerSec" : 0.01609428191912443,
    "sentKBytesPerSec" : 0.060549298463300566
  },
  "https://demoqa.com/BookStore/v1/Book" : {
    "transaction" : "https://demoqa.com/BookStore/v1/Book",
    "sampleCount" : 14,
    "errorCount" : 0,
    "errorPct" : 0.0,
    "meanResTime" : 273.57142857142856,
    "medianResTime" : 264.5,
    "minResTime" : 240.0,
    "maxResTime" : 373.0,
    "pct1ResTime" : 357.5,
    "pct2ResTime" : 373.0,
    "pct3ResTime" : 373.0,
    "throughput" : 0.08901322482197355,
    "receivedKBytesPerSec" : 0.01608149081256358,
    "sentKBytesPerSec" : 0.060501176246185145
  },
  "https://demoqa.com/books?book=9781449337711-4" : {
    "transaction" : "https://demoqa.com/books?book=9781449337711-4",
    "sampleCount" : 17,
    "errorCount" : 0,
    "errorPct" : 0.0,
    "meanResTime" : 85.88235294117648,
    "medianResTime" : 70.0,
    "minResTime" : 52.0,
    "maxResTime" : 225.0,
    "pct1ResTime" : 180.19999999999996,
    "pct2ResTime" : 225.0,
    "pct3ResTime" : 225.0,
    "throughput" : 0.09034143749169657,
    "receivedKBytesPerSec" : 12.984459072339577,
    "sentKBytesPerSec" : 0.052399902019396837
  },
  "https://demoqa.com/books?book=9781449337711-7" : {
    "transaction" : "https://demoqa.com/books?book=9781449337711-7",
    "sampleCount" : 17,
    "errorCount" : 0,
    "errorPct" : 0.0,
    "meanResTime" : 443.764705882353,
    "medianResTime" : 443.0,
    "minResTime" : 442.0,
    "maxResTime" : 452.0,
    "pct1ResTime" : 447.2,
    "pct2ResTime" : 452.0,
    "pct3ResTime" : 452.0,
    "throughput" : 0.09015411049712037,
    "receivedKBytesPerSec" : 0.03021364204045268,
    "sentKBytesPerSec" : 0.050343985991642186
  },
  "https://demoqa.com/books?book=9781449337711-6" : {
    "transaction" : "https://demoqa.com/books?book=9781449337711-6",
    "sampleCount" : 17,
    "errorCount" : 0,
    "errorPct" : 0.0,
    "meanResTime" : 21.23529411764706,
    "medianResTime" : 15.0,
    "minResTime" : 9.0,
    "maxResTime" : 78.0,
    "pct1ResTime" : 46.79999999999997,
    "pct2ResTime" : 78.0,
    "pct3ResTime" : 78.0,
    "throughput" : 0.0903620861947994,
    "receivedKBytesPerSec" : 0.0671850000930198,
    "sentKBytesPerSec" : 0.05116607787351434
  },
  "https://demoqa.com/books?book=9781449337711-1" : {
    "transaction" : "https://demoqa.com/books?book=9781449337711-1",
    "sampleCount" : 17,
    "errorCount" : 0,
    "errorPct" : 0.0,
    "meanResTime" : 30.411764705882348,
    "medianResTime" : 22.0,
    "minResTime" : 7.0,
    "maxResTime" : 164.0,
    "pct1ResTime" : 72.79999999999993,
    "pct2ResTime" : 164.0,
    "pct3ResTime" : 164.0,
    "throughput" : 0.09035776359219946,
    "receivedKBytesPerSec" : 1.4247905742900273,
    "sentKBytesPerSec" : 0.04971545609409964
  },
  "https://demoqa.com/books?book=9781449337711-0" : {
    "transaction" : "https://demoqa.com/books?book=9781449337711-0",
    "sampleCount" : 17,
    "errorCount" : 0,
    "errorPct" : 0.0,
    "meanResTime" : 200.8235294117647,
    "medianResTime" : 149.0,
    "minResTime" : 148.0,
    "maxResTime" : 445.0,
    "pct1ResTime" : 443.4,
    "pct2ResTime" : 445.0,
    "pct3ResTime" : 445.0,
    "throughput" : 0.09029393330996313,
    "receivedKBytesPerSec" : 0.30297847153616536,
    "sentKBytesPerSec" : 0.04532332199347759
  },
  "https://demoqa.com/books?book=9781449337711-3" : {
    "transaction" : "https://demoqa.com/books?book=9781449337711-3",
    "sampleCount" : 17,
    "errorCount" : 0,
    "errorPct" : 0.0,
    "meanResTime" : 22.176470588235293,
    "medianResTime" : 12.0,
    "minResTime" : 9.0,
    "maxResTime" : 71.0,
    "pct1ResTime" : 71.0,
    "pct2ResTime" : 71.0,
    "pct3ResTime" : 71.0,
    "throughput" : 0.09036064528131395,
    "receivedKBytesPerSec" : 2.560069481356473,
    "sentKBytesPerSec" : 0.05237470765673586
  },
  "https://demoqa.com/books?book=9781449337711-2" : {
    "transaction" : "https://demoqa.com/books?book=9781449337711-2",
    "sampleCount" : 17,
    "errorCount" : 0,
    "errorPct" : 0.0,
    "meanResTime" : 20.29411764705882,
    "medianResTime" : 19.0,
    "minResTime" : 6.0,
    "maxResTime" : 59.0,
    "pct1ResTime" : 36.59999999999998,
    "pct2ResTime" : 59.0,
    "pct3ResTime" : 59.0,
    "throughput" : 0.09035488208687888,
    "receivedKBytesPerSec" : 3.9767670857095783,
    "sentKBytesPerSec" : 0.050331530997039554
  },
  "https://demoqa.com/books?book=9781449337711-9" : {
    "transaction" : "https://demoqa.com/books?book=9781449337711-9",
    "sampleCount" : 17,
    "errorCount" : 0,
    "errorPct" : 0.0,
    "meanResTime" : 32.76470588235295,
    "medianResTime" : 28.0,
    "minResTime" : 25.0,
    "maxResTime" : 60.0,
    "pct1ResTime" : 56.8,
    "pct2ResTime" : 60.0,
    "pct3ResTime" : 60.0,
    "throughput" : 0.09035248097283048,
    "receivedKBytesPerSec" : 0.1358297579882223,
    "sentKBytesPerSec" : 0.04835269489561631
  },
  "https://demoqa.com/books?book=9781449337711-8" : {
    "transaction" : "https://demoqa.com/books?book=9781449337711-8",
    "sampleCount" : 17,
    "errorCount" : 0,
    "errorPct" : 0.0,
    "meanResTime" : 460.0,
    "medianResTime" : 442.0,
    "minResTime" : 147.0,
    "maxResTime" : 745.0,
    "pct1ResTime" : 739.4,
    "pct2ResTime" : 745.0,
    "pct3ResTime" : 745.0,
    "throughput" : 0.09015506671474938,
    "receivedKBytesPerSec" : 0.8755679023435015,
    "sentKBytesPerSec" : 0.0501528990157188
  },
  "goToProfile" : {
    "transaction" : "goToProfile",
    "sampleCount" : 16,
    "errorCount" : 0,
    "errorPct" : 0.0,
    "meanResTime" : 178.375,
    "medianResTime" : 178.0,
    "minResTime" : 173.0,
    "maxResTime" : 184.0,
    "pct1ResTime" : 184.0,
    "pct2ResTime" : 184.0,
    "pct3ResTime" : 184.0,
    "throughput" : 0.08288609378561512,
    "receivedKBytesPerSec" : 0.1659644282672662,
    "sentKBytesPerSec" : 0.05358456453718477
  },
  "https://demoqa.com/books?book=9781449331818-0" : {
    "transaction" : "https://demoqa.com/books?book=9781449331818-0",
    "sampleCount" : 17,
    "errorCount" : 0,
    "errorPct" : 0.0,
    "meanResTime" : 219.58823529411765,
    "medianResTime" : 150.0,
    "minResTime" : 149.0,
    "maxResTime" : 451.0,
    "pct1ResTime" : 446.2,
    "pct2ResTime" : 451.0,
    "pct3ResTime" : 451.0,
    "throughput" : 0.0771265374267865,
    "receivedKBytesPerSec" : 0.2587956861312875,
    "sentKBytesPerSec" : 0.03871390648180494
  },
  "https://demoqa.com/books?book=9781449331818-1" : {
    "transaction" : "https://demoqa.com/books?book=9781449331818-1",
    "sampleCount" : 17,
    "errorCount" : 1,
    "errorPct" : 5.882353,
    "meanResTime" : 56.529411764705884,
    "medianResTime" : 23.0,
    "minResTime" : 6.0,
    "maxResTime" : 635.0,
    "pct1ResTime" : 151.79999999999956,
    "pct2ResTime" : 635.0,
    "pct3ResTime" : 635.0,
    "throughput" : 0.07717135217827491,
    "receivedKBytesPerSec" : 0.4303783538329195,
    "sentKBytesPerSec" : 0.04210998818597388
  },
  "https://demoqa.com/books-10" : {
    "transaction" : "https://demoqa.com/books-10",
    "sampleCount" : 54,
    "errorCount" : 0,
    "errorPct" : 0.0,
    "meanResTime" : 1292.6481481481485,
    "medianResTime" : 1323.0,
    "minResTime" : 883.0,
    "maxResTime" : 1490.0,
    "pct1ResTime" : 1469.5,
    "pct2ResTime" : 1481.75,
    "pct3ResTime" : 1490.0,
    "throughput" : 0.24921888340709905,
    "receivedKBytesPerSec" : 192.98716919366154,
    "sentKBytesPerSec" : 0.12144553009779534
  },
  "https://demoqa.com/books?book=9781491950296-0" : {
    "transaction" : "https://demoqa.com/books?book=9781491950296-0",
    "sampleCount" : 12,
    "errorCount" : 0,
    "errorPct" : 0.0,
    "meanResTime" : 199.08333333333331,
    "medianResTime" : 150.0,
    "minResTime" : 148.0,
    "maxResTime" : 444.0,
    "pct1ResTime" : 443.4,
    "pct2ResTime" : 444.0,
    "pct3ResTime" : 444.0,
    "throughput" : 0.05664091078584544,
    "receivedKBytesPerSec" : 0.1900568061134423,
    "sentKBytesPerSec" : 0.028431082171801323
  },
  "https://demoqa.com/Account/v1/User/862f2311-cdfa-4a28-9eb4-58aba5e04c19" : {
    "transaction" : "https://demoqa.com/Account/v1/User/862f2311-cdfa-4a28-9eb4-58aba5e04c19",
    "sampleCount" : 1,
    "errorCount" : 0,
    "errorPct" : 0.0,
    "meanResTime" : 178.0,
    "medianResTime" : 178.0,
    "minResTime" : 178.0,
    "maxResTime" : 178.0,
    "pct1ResTime" : 178.0,
    "pct2ResTime" : 178.0,
    "pct3ResTime" : 178.0,
    "throughput" : 5.617977528089887,
    "receivedKBytesPerSec" : 1.794022120786517,
    "sentKBytesPerSec" : 3.352133075842697
  },
  "https://demoqa.com/books?book=9781491950296-1" : {
    "transaction" : "https://demoqa.com/books?book=9781491950296-1",
    "sampleCount" : 12,
    "errorCount" : 0,
    "errorPct" : 0.0,
    "meanResTime" : 18.083333333333332,
    "medianResTime" : 16.0,
    "minResTime" : 6.0,
    "maxResTime" : 32.0,
    "pct1ResTime" : 31.400000000000002,
    "pct2ResTime" : 32.0,
    "pct3ResTime" : 32.0,
    "throughput" : 0.056677561353460165,
    "receivedKBytesPerSec" : 0.431640588100546,
    "sentKBytesPerSec" : 0.03207023796310291
  },
  "https://demoqa.com/books?book=9781449331818-8" : {
    "transaction" : "https://demoqa.com/books?book=9781449331818-8",
    "sampleCount" : 17,
    "errorCount" : 0,
    "errorPct" : 0.0,
    "meanResTime" : 453.29411764705884,
    "medianResTime" : 443.0,
    "minResTime" : 154.0,
    "maxResTime" : 752.0,
    "pct1ResTime" : 629.5999999999999,
    "pct2ResTime" : 752.0,
    "pct3ResTime" : 752.0,
    "throughput" : 0.07702694130547072,
    "receivedKBytesPerSec" : 0.2631473590520249,
    "sentKBytesPerSec" : 0.04361969137117017
  },
  "https://demoqa.com/books?book=9781491950296-2" : {
    "transaction" : "https://demoqa.com/books?book=9781491950296-2",
    "sampleCount" : 12,
    "errorCount" : 0,
    "errorPct" : 0.0,
    "meanResTime" : 17.583333333333332,
    "medianResTime" : 17.5,
    "minResTime" : 6.0,
    "maxResTime" : 31.0,
    "pct1ResTime" : 30.1,
    "pct2ResTime" : 31.0,
    "pct3ResTime" : 31.0,
    "throughput" : 0.05667702596752406,
    "receivedKBytesPerSec" : 1.1875746468903206,
    "sentKBytesPerSec" : 0.032457375629351144
  },
  "https://demoqa.com/books?book=9781449325862-8" : {
    "transaction" : "https://demoqa.com/books?book=9781449325862-8",
    "sampleCount" : 16,
    "errorCount" : 0,
    "errorPct" : 0.0,
    "meanResTime" : 608.1875,
    "medianResTime" : 735.0,
    "minResTime" : 148.0,
    "maxResTime" : 745.0,
    "pct1ResTime" : 740.8,
    "pct2ResTime" : 745.0,
    "pct3ResTime" : 745.0,
    "throughput" : 0.08323709044750341,
    "receivedKBytesPerSec" : 2.8062035693104845,
    "sentKBytesPerSec" : 0.043132501092486814
  },
  "https://demoqa.com/books?book=9781449331818-9" : {
    "transaction" : "https://demoqa.com/books?book=9781449331818-9",
    "sampleCount" : 17,
    "errorCount" : 0,
    "errorPct" : 0.0,
    "meanResTime" : 37.705882352941174,
    "medianResTime" : 36.0,
    "minResTime" : 23.0,
    "maxResTime" : 66.0,
    "pct1ResTime" : 57.99999999999999,
    "pct2ResTime" : 66.0,
    "pct3ResTime" : 66.0,
    "throughput" : 0.07716995092899002,
    "receivedKBytesPerSec" : 0.11601204134947547,
    "sentKBytesPerSec" : 0.04129798155184232
  },
  "https://demoqa.com/books?book=9781449331818-10" : {
    "transaction" : "https://demoqa.com/books?book=9781449331818-10",
    "sampleCount" : 17,
    "errorCount" : 0,
    "errorPct" : 0.0,
    "meanResTime" : 476.76470588235287,
    "medianResTime" : 442.0,
    "minResTime" : 147.0,
    "maxResTime" : 1321.0,
    "pct1ResTime" : 621.7999999999994,
    "pct2ResTime" : 1321.0,
    "pct3ResTime" : 1321.0,
    "throughput" : 0.07702519630097822,
    "receivedKBytesPerSec" : 3.5281194708935377,
    "sentKBytesPerSec" : 0.04376471832565347
  },
  "https://demoqa.com/books?book=9781491950296-3" : {
    "transaction" : "https://demoqa.com/books?book=9781491950296-3",
    "sampleCount" : 12,
    "errorCount" : 0,
    "errorPct" : 0.0,
    "meanResTime" : 14.499999999999998,
    "medianResTime" : 10.5,
    "minResTime" : 9.0,
    "maxResTime" : 38.0,
    "pct1ResTime" : 32.60000000000002,
    "pct2ResTime" : 38.0,
    "pct3ResTime" : 38.0,
    "throughput" : 0.056678899862553665,
    "receivedKBytesPerSec" : 0.783135606629542,
    "sentKBytesPerSec" : 0.03332560640518801
  },
  "https://demoqa.com/books?book=9781449325862-9" : {
    "transaction" : "https://demoqa.com/books?book=9781449325862-9",
    "sampleCount" : 16,
    "errorCount" : 0,
    "errorPct" : 0.0,
    "meanResTime" : 42.625,
    "medianResTime" : 29.0,
    "minResTime" : 26.0,
    "maxResTime" : 160.0,
    "pct1ResTime" : 99.10000000000007,
    "pct2ResTime" : 160.0,
    "pct3ResTime" : 160.0,
    "throughput" : 0.08341805479523474,
    "receivedKBytesPerSec" : 0.1202800370167618,
    "sentKBytesPerSec" : 0.04464169338651234
  },
  "https://demoqa.com/books?book=9781449331818-6" : {
    "transaction" : "https://demoqa.com/books?book=9781449331818-6",
    "sampleCount" : 17,
    "errorCount" : 0,
    "errorPct" : 0.0,
    "meanResTime" : 14.294117647058824,
    "medianResTime" : 11.0,
    "minResTime" : 9.0,
    "maxResTime" : 53.0,
    "pct1ResTime" : 25.799999999999976,
    "pct2ResTime" : 53.0,
    "pct3ResTime" : 53.0,
    "throughput" : 0.07717695768432808,
    "receivedKBytesPerSec" : 0.05048777539689386,
    "sentKBytesPerSec" : 0.04446275899679035
  },
  "https://demoqa.com/Account/v1/User/bbe48237-e997-45ee-a696-457dd520fc5e" : {
    "transaction" : "https://demoqa.com/Account/v1/User/bbe48237-e997-45ee-a696-457dd520fc5e",
    "sampleCount" : 3,
    "errorCount" : 0,
    "errorPct" : 0.0,
    "meanResTime" : 303.3333333333333,
    "medianResTime" : 180.0,
    "minResTime" : 175.0,
    "maxResTime" : 555.0,
    "pct1ResTime" : 555.0,
    "pct2ResTime" : 555.0,
    "pct3ResTime" : 555.0,
    "throughput" : 0.07865963973885,
    "receivedKBytesPerSec" : 0.03559143855371142,
    "sentKBytesPerSec" : 0.05044254241065575
  },
  "https://demoqa.com/books?book=9781491950296-4" : {
    "transaction" : "https://demoqa.com/books?book=9781491950296-4",
    "sampleCount" : 12,
    "errorCount" : 0,
    "errorPct" : 0.0,
    "meanResTime" : 61.0,
    "medianResTime" : 54.5,
    "minResTime" : 51.0,
    "maxResTime" : 102.0,
    "pct1ResTime" : 94.50000000000003,
    "pct2ResTime" : 102.0,
    "pct3ResTime" : 102.0,
    "throughput" : 0.05666096909144136,
    "receivedKBytesPerSec" : 8.143967591401225,
    "sentKBytesPerSec" : 0.03305223197000746
  },
  "https://demoqa.com/books?book=9781449325862-6" : {
    "transaction" : "https://demoqa.com/books?book=9781449325862-6",
    "sampleCount" : 16,
    "errorCount" : 0,
    "errorPct" : 0.0,
    "meanResTime" : 36.50000000000001,
    "medianResTime" : 34.5,
    "minResTime" : 10.0,
    "maxResTime" : 121.0,
    "pct1ResTime" : 76.20000000000005,
    "pct2ResTime" : 121.0,
    "pct3ResTime" : 121.0,
    "throughput" : 0.08340544429037607,
    "receivedKBytesPerSec" : 0.09114834472773335,
    "sentKBytesPerSec" : 0.04408515304899027
  },
  "https://demoqa.com/books?book=9781449331818-7" : {
    "transaction" : "https://demoqa.com/books?book=9781449331818-7",
    "sampleCount" : 17,
    "errorCount" : 0,
    "errorPct" : 0.0,
    "meanResTime" : 400.8823529411764,
    "medianResTime" : 443.0,
    "minResTime" : 148.0,
    "maxResTime" : 597.0,
    "pct1ResTime" : 475.39999999999986,
    "pct2ResTime" : 597.0,
    "pct3ResTime" : 597.0,
    "throughput" : 0.07712688734030197,
    "receivedKBytesPerSec" : 0.02237424064042538,
    "sentKBytesPerSec" : 0.04383135894172837
  },
  "https://demoqa.com/books?book=9781491950296-5" : {
    "transaction" : "https://demoqa.com/books?book=9781491950296-5",
    "sampleCount" : 12,
    "errorCount" : 0,
    "errorPct" : 0.0,
    "meanResTime" : 41.91666666666667,
    "medianResTime" : 33.5,
    "minResTime" : 22.0,
    "maxResTime" : 106.0,
    "pct1ResTime" : 101.50000000000001,
    "pct2ResTime" : 106.0,
    "pct3ResTime" : 106.0,
    "throughput" : 0.05667086975617358,
    "receivedKBytesPerSec" : 0.7909017575053483,
    "sentKBytesPerSec" : 0.032190972566576465
  },
  "https://demoqa.com/books?book=9781449325862-7" : {
    "transaction" : "https://demoqa.com/books?book=9781449325862-7",
    "sampleCount" : 16,
    "errorCount" : 0,
    "errorPct" : 0.0,
    "meanResTime" : 444.99999999999994,
    "medianResTime" : 443.0,
    "minResTime" : 147.0,
    "maxResTime" : 603.0,
    "pct1ResTime" : 601.6,
    "pct2ResTime" : 603.0,
    "pct3ResTime" : 603.0,
    "throughput" : 0.08323449237363963,
    "receivedKBytesPerSec" : 0.042186231974530246,
    "sentKBytesPerSec" : 0.043344524470940754
  },
  "https://demoqa.com/books?book=9781449331818-4" : {
    "transaction" : "https://demoqa.com/books?book=9781449331818-4",
    "sampleCount" : 17,
    "errorCount" : 0,
    "errorPct" : 0.0,
    "meanResTime" : 79.8235294117647,
    "medianResTime" : 60.0,
    "minResTime" : 49.0,
    "maxResTime" : 171.0,
    "pct1ResTime" : 146.2,
    "pct2ResTime" : 171.0,
    "pct3ResTime" : 171.0,
    "throughput" : 0.07716259520502555,
    "receivedKBytesPerSec" : 11.09226933632225,
    "sentKBytesPerSec" : 0.04505731734025074
  },
  "https://demoqa.com/books?book=9781491950296-6" : {
    "transaction" : "https://demoqa.com/books?book=9781491950296-6",
    "sampleCount" : 12,
    "errorCount" : 0,
    "errorPct" : 0.0,
    "meanResTime" : 15.500000000000002,
    "medianResTime" : 14.0,
    "minResTime" : 10.0,
    "maxResTime" : 34.0,
    "pct1ResTime" : 29.200000000000017,
    "pct2ResTime" : 34.0,
    "pct3ResTime" : 34.0,
    "throughput" : 0.05667970299835629,
    "receivedKBytesPerSec" : 0.03814625193655652,
    "sentKBytesPerSec" : 0.032537322994010846
  },
  "https://demoqa.com/books?book=9781449325862-4" : {
    "transaction" : "https://demoqa.com/books?book=9781449325862-4",
    "sampleCount" : 16,
    "errorCount" : 0,
    "errorPct" : 0.0,
    "meanResTime" : 90.31249999999997,
    "medianResTime" : 89.0,
    "minResTime" : 51.0,
    "maxResTime" : 238.0,
    "pct1ResTime" : 153.30000000000007,
    "pct2ResTime" : 238.0,
    "pct3ResTime" : 238.0,
    "throughput" : 0.08338544923910778,
    "receivedKBytesPerSec" : 11.985441951024077,
    "sentKBytesPerSec" : 0.04702646185115698
  },
  "https://demoqa.com/books?book=9781449331818-5" : {
    "transaction" : "https://demoqa.com/books?book=9781449331818-5",
    "sampleCount" : 17,
    "errorCount" : 0,
    "errorPct" : 0.0,
    "meanResTime" : 37.94117647058823,
    "medianResTime" : 35.0,
    "minResTime" : 20.0,
    "maxResTime" : 105.0,
    "pct1ResTime" : 64.99999999999997,
    "pct2ResTime" : 105.0,
    "pct3ResTime" : 105.0,
    "throughput" : 0.07717030123654059,
    "receivedKBytesPerSec" : 0.4032777730807292,
    "sentKBytesPerSec" : 0.04454758485328564
  },
  "https://demoqa.com/books?book=9781491950296-7" : {
    "transaction" : "https://demoqa.com/books?book=9781491950296-7",
    "sampleCount" : 12,
    "errorCount" : 0,
    "errorPct" : 0.0,
    "meanResTime" : 442.9166666666667,
    "medianResTime" : 442.0,
    "minResTime" : 441.0,
    "maxResTime" : 448.0,
    "pct1ResTime" : 447.4,
    "pct2ResTime" : 448.0,
    "pct3ResTime" : 448.0,
    "throughput" : 0.05656535183648842,
    "receivedKBytesPerSec" : 0.016940144430198357,
    "sentKBytesPerSec" : 0.032029762213402216
  },
  "https://demoqa.com/books?book=9781449325862-5" : {
    "transaction" : "https://demoqa.com/books?book=9781449325862-5",
    "sampleCount" : 16,
    "errorCount" : 0,
    "errorPct" : 0.0,
    "meanResTime" : 61.62499999999999,
    "medianResTime" : 66.0,
    "minResTime" : 19.0,
    "maxResTime" : 120.0,
    "pct1ResTime" : 114.4,
    "pct2ResTime" : 120.0,
    "pct3ResTime" : 120.0,
    "throughput" : 0.0834002272656193,
    "receivedKBytesPerSec" : 4.245384115058433,
    "sentKBytesPerSec" : 0.04460161079720192
  },
  "https://demoqa.com/books?book=9781449331818-2" : {
    "transaction" : "https://demoqa.com/books?book=9781449331818-2",
    "sampleCount" : 17,
    "errorCount" : 1,
    "errorPct" : 5.882353,
    "meanResTime" : 57.0,
    "medianResTime" : 21.0,
    "minResTime" : 8.0,
    "maxResTime" : 638.0,
    "pct1ResTime" : 156.39999999999958,
    "pct2ResTime" : 638.0,
    "pct3ResTime" : 638.0,
    "throughput" : 0.07717380448697579,
    "receivedKBytesPerSec" : 1.156968681054285,
    "sentKBytesPerSec" : 0.04260784897313444
  },
  "https://demoqa.com/books?book=9781491950296-8" : {
    "transaction" : "https://demoqa.com/books?book=9781491950296-8",
    "sampleCount" : 12,
    "errorCount" : 0,
    "errorPct" : 0.0,
    "meanResTime" : 417.75000000000006,
    "medianResTime" : 441.5,
    "minResTime" : 148.0,
    "maxResTime" : 734.0,
    "pct1ResTime" : 647.9000000000003,
    "pct2ResTime" : 734.0,
    "pct3ResTime" : 734.0,
    "throughput" : 0.05656668505083931,
    "receivedKBytesPerSec" : 0.26743962684843425,
    "sentKBytesPerSec" : 0.03191543192199454
  },
  "https://demoqa.com/books?book=9781449325862-2" : {
    "transaction" : "https://demoqa.com/books?book=9781449325862-2",
    "sampleCount" : 16,
    "errorCount" : 0,
    "errorPct" : 0.0,
    "meanResTime" : 30.999999999999996,
    "medianResTime" : 36.5,
    "minResTime" : 6.0,
    "maxResTime" : 52.0,
    "pct1ResTime" : 51.3,
    "pct2ResTime" : 52.0,
    "pct3ResTime" : 52.0,
    "throughput" : 0.08340500951338391,
    "receivedKBytesPerSec" : 12.93235295794563,
    "sentKBytesPerSec" : 0.04503178186983606
  },
  "https://demoqa.com/books?book=9781449331818-3" : {
    "transaction" : "https://demoqa.com/books?book=9781449331818-3",
    "sampleCount" : 17,
    "errorCount" : 0,
    "errorPct" : 0.0,
    "meanResTime" : 13.352941176470587,
    "medianResTime" : 11.0,
    "minResTime" : 9.0,
    "maxResTime" : 38.0,
    "pct1ResTime" : 21.999999999999986,
    "pct2ResTime" : 38.0,
    "pct3ResTime" : 38.0,
    "throughput" : 0.07717765842984324,
    "receivedKBytesPerSec" : 0.7714618086924743,
    "sentKBytesPerSec" : 0.045411922983506686
  },
  "https://demoqa.com/books?book=9781491950296-9" : {
    "transaction" : "https://demoqa.com/books?book=9781491950296-9",
    "sampleCount" : 12,
    "errorCount" : 0,
    "errorPct" : 0.0,
    "meanResTime" : 33.16666666666667,
    "medianResTime" : 27.0,
    "minResTime" : 25.0,
    "maxResTime" : 78.0,
    "pct1ResTime" : 69.00000000000003,
    "pct2ResTime" : 78.0,
    "pct3ResTime" : 78.0,
    "throughput" : 0.056678899862553665,
    "receivedKBytesPerSec" : 0.0825829283153614,
    "sentKBytesPerSec" : 0.030332067504569737
  },
  "https://demoqa.com/books?book=9781449325862-3" : {
    "transaction" : "https://demoqa.com/books?book=9781449325862-3",
    "sampleCount" : 16,
    "errorCount" : 0,
    "errorPct" : 0.0,
    "meanResTime" : 45.1875,
    "medianResTime" : 47.5,
    "minResTime" : 10.0,
    "maxResTime" : 163.0,
    "pct1ResTime" : 97.20000000000007,
    "pct2ResTime" : 163.0,
    "pct3ResTime" : 163.0,
    "throughput" : 0.08340240094661726,
    "receivedKBytesPerSec" : 8.19412808816937,
    "sentKBytesPerSec" : 0.045753221417736564
  },
  "deleteBooks" : {
    "transaction" : "deleteBooks",
    "sampleCount" : 14,
    "errorCount" : 0,
    "errorPct" : 0.0,
    "meanResTime" : 269.14285714285717,
    "medianResTime" : 252.5,
    "minResTime" : 176.0,
    "maxResTime" : 544.0,
    "pct1ResTime" : 461.5,
    "pct2ResTime" : 544.0,
    "pct3ResTime" : 544.0,
    "throughput" : 0.08910727242639103,
    "receivedKBytesPerSec" : 0.016098481834846034,
    "sentKBytesPerSec" : 0.061435287434601624
  },
  "https://demoqa.com/BookStore/v1/Books?UserId=02890277-743b-4466-8bcc-16dfd3bcdd9d" : {
    "transaction" : "https://demoqa.com/BookStore/v1/Books?UserId=02890277-743b-4466-8bcc-16dfd3bcdd9d",
    "sampleCount" : 1,
    "errorCount" : 0,
    "errorPct" : 0.0,
    "meanResTime" : 544.0,
    "medianResTime" : 544.0,
    "minResTime" : 544.0,
    "maxResTime" : 544.0,
    "pct1ResTime" : 544.0,
    "pct2ResTime" : 544.0,
    "pct3ResTime" : 544.0,
    "throughput" : 1.838235294117647,
    "receivedKBytesPerSec" : 0.33210305606617646,
    "sentKBytesPerSec" : 1.2673770680147058
  },
  "https://demoqa.com/books?book=9781491950296" : {
    "transaction" : "https://demoqa.com/books?book=9781491950296",
    "sampleCount" : 12,
    "errorCount" : 0,
    "errorPct" : 0.0,
    "meanResTime" : 748.9166666666666,
    "medianResTime" : 612.0,
    "minResTime" : 608.0,
    "maxResTime" : 1659.0,
    "pct1ResTime" : 1432.2000000000007,
    "pct2ResTime" : 1659.0,
    "pct3ResTime" : 1659.0,
    "throughput" : 0.05651766412494171,
    "receivedKBytesPerSec" : 15.562949234480014,
    "sentKBytesPerSec" : 0.34959266071033285
  },
  "https://demoqa.com/BookStore/v1/Books?UserId=11482878-8094-49f3-9232-a159276abe53" : {
    "transaction" : "https://demoqa.com/BookStore/v1/Books?UserId=11482878-8094-49f3-9232-a159276abe53",
    "sampleCount" : 1,
    "errorCount" : 0,
    "errorPct" : 0.0,
    "meanResTime" : 250.0,
    "medianResTime" : 250.0,
    "minResTime" : 250.0,
    "maxResTime" : 250.0,
    "pct1ResTime" : 250.0,
    "pct2ResTime" : 250.0,
    "pct3ResTime" : 250.0,
    "throughput" : 4.0,
    "receivedKBytesPerSec" : 0.72265625,
    "sentKBytesPerSec" : 2.7578125
  },
  "https://demoqa.com/Account/v1/User/6e37b490-4af4-4cfe-ac35-986adefdbfee" : {
    "transaction" : "https://demoqa.com/Account/v1/User/6e37b490-4af4-4cfe-ac35-986adefdbfee",
    "sampleCount" : 1,
    "errorCount" : 0,
    "errorPct" : 0.0,
    "meanResTime" : 199.0,
    "medianResTime" : 199.0,
    "minResTime" : 199.0,
    "maxResTime" : 199.0,
    "pct1ResTime" : 199.0,
    "pct2ResTime" : 199.0,
    "pct3ResTime" : 199.0,
    "throughput" : 5.025125628140704,
    "receivedKBytesPerSec" : 1.6047032035175879,
    "sentKBytesPerSec" : 2.998390389447236
  },
  "https://demoqa.com/Account/v1/User/8e6477c4-07e6-41e4-952a-46ac16081c2f" : {
    "transaction" : "https://demoqa.com/Account/v1/User/8e6477c4-07e6-41e4-952a-46ac16081c2f",
    "sampleCount" : 3,
    "errorCount" : 0,
    "errorPct" : 0.0,
    "meanResTime" : 239.66666666666666,
    "medianResTime" : 180.0,
    "minResTime" : 179.0,
    "maxResTime" : 360.0,
    "pct1ResTime" : 360.0,
    "pct2ResTime" : 360.0,
    "pct3ResTime" : 360.0,
    "throughput" : 0.07629510948348212,
    "receivedKBytesPerSec" : 0.0353659622084891,
    "sentKBytesPerSec" : 0.04892622580809237
  },
  "https://demoqa.com/Account/v1/Login" : {
    "transaction" : "https://demoqa.com/Account/v1/Login",
    "sampleCount" : 23,
    "errorCount" : 0,
    "errorPct" : 0.0,
    "meanResTime" : 236.17391304347825,
    "medianResTime" : 240.0,
    "minResTime" : 154.0,
    "maxResTime" : 348.0,
    "pct1ResTime" : 277.2,
    "pct2ResTime" : 334.3999999999998,
    "pct3ResTime" : 348.0,
    "throughput" : 0.10000173916068106,
    "receivedKBytesPerSec" : 0.06142684954303553,
    "sentKBytesPerSec" : 0.0452156301087845
  },
  "https://demoqa.com/books?book=9781449325862-0" : {
    "transaction" : "https://demoqa.com/books?book=9781449325862-0",
    "sampleCount" : 16,
    "errorCount" : 0,
    "errorPct" : 0.0,
    "meanResTime" : 168.0,
    "medianResTime" : 150.0,
    "minResTime" : 148.0,
    "maxResTime" : 443.0,
    "pct1ResTime" : 238.6000000000002,
    "pct2ResTime" : 443.0,
    "pct3ResTime" : 443.0,
    "throughput" : 0.08333984425866604,
    "receivedKBytesPerSec" : 0.2796442430398208,
    "sentKBytesPerSec" : 0.041832695262650724
  },
  "https://demoqa.com/BookStore/v1/Books?UserId=6d10803b-2153-4c4b-87f2-567147cdacd9" : {
    "transaction" : "https://demoqa.com/BookStore/v1/Books?UserId=6d10803b-2153-4c4b-87f2-567147cdacd9",
    "sampleCount" : 1,
    "errorCount" : 0,
    "errorPct" : 0.0,
    "meanResTime" : 252.0,
    "medianResTime" : 252.0,
    "minResTime" : 252.0,
    "maxResTime" : 252.0,
    "pct1ResTime" : 252.0,
    "pct2ResTime" : 252.0,
    "pct3ResTime" : 252.0,
    "throughput" : 3.968253968253968,
    "receivedKBytesPerSec" : 0.7169208829365079,
    "sentKBytesPerSec" : 2.7359250992063493
  },
  "https://demoqa.com/books?book=9781449325862-1" : {
    "transaction" : "https://demoqa.com/books?book=9781449325862-1",
    "sampleCount" : 16,
    "errorCount" : 0,
    "errorPct" : 0.0,
    "meanResTime" : 30.0625,
    "medianResTime" : 32.0,
    "minResTime" : 5.0,
    "maxResTime" : 62.0,
    "pct1ResTime" : 52.20000000000001,
    "pct2ResTime" : 62.0,
    "pct3ResTime" : 62.0,
    "throughput" : 0.0834041399729979,
    "receivedKBytesPerSec" : 4.5891061242747755,
    "sentKBytesPerSec" : 0.044461166902109606
  },
  "https://demoqa.com/BookStore/v1/Books?UserId=59d17239-7489-45f1-abe3-02f9500dab7d" : {
    "transaction" : "https://demoqa.com/BookStore/v1/Books?UserId=59d17239-7489-45f1-abe3-02f9500dab7d",
    "sampleCount" : 1,
    "errorCount" : 0,
    "errorPct" : 0.0,
    "meanResTime" : 269.0,
    "medianResTime" : 269.0,
    "minResTime" : 269.0,
    "maxResTime" : 269.0,
    "pct1ResTime" : 269.0,
    "pct2ResTime" : 269.0,
    "pct3ResTime" : 269.0,
    "throughput" : 3.717472118959108,
    "receivedKBytesPerSec" : 0.6716136152416357,
    "sentKBytesPerSec" : 2.5630227695167282
  },
  "login" : {
    "transaction" : "login",
    "sampleCount" : 23,
    "errorCount" : 0,
    "errorPct" : 0.0,
    "meanResTime" : 836.8695652173913,
    "medianResTime" : 834.0,
    "minResTime" : 700.0,
    "maxResTime" : 1102.0,
    "pct1ResTime" : 936.6,
    "pct2ResTime" : 1070.9999999999995,
    "pct3ResTime" : 1102.0,
    "throughput" : 0.10060142154182614,
    "receivedKBytesPerSec" : 0.14598995352651722,
    "sentKBytesPerSec" : 0.15178632449425916
  },
  "https://demoqa.com/BookStore/v1/Book?ISBN=9781449331818" : {
    "transaction" : "https://demoqa.com/BookStore/v1/Book?ISBN=9781449331818",
    "sampleCount" : 17,
    "errorCount" : 0,
    "errorPct" : 0.0,
    "meanResTime" : 239.8235294117647,
    "medianResTime" : 152.0,
    "minResTime" : 150.0,
    "maxResTime" : 460.0,
    "pct1ResTime" : 456.0,
    "pct2ResTime" : 460.0,
    "pct3ResTime" : 460.0,
    "throughput" : 0.07665219292906066,
    "receivedKBytesPerSec" : 0.062055339783389916,
    "sentKBytesPerSec" : 0.02724745920525203
  },
  "https://demoqa.com/books?book=9781449337711-10" : {
    "transaction" : "https://demoqa.com/books?book=9781449337711-10",
    "sampleCount" : 17,
    "errorCount" : 0,
    "errorPct" : 0.0,
    "meanResTime" : 588.7058823529412,
    "medianResTime" : 442.0,
    "minResTime" : 440.0,
    "maxResTime" : 1324.0,
    "pct1ResTime" : 1322.4,
    "pct2ResTime" : 1324.0,
    "pct3ResTime" : 1324.0,
    "throughput" : 0.09015506671474938,
    "receivedKBytesPerSec" : 12.339990293414969,
    "sentKBytesPerSec" : 0.050313446296748054
  },
  "https://demoqa.com/Account/v1/User/0be52525-ba27-442d-b9c7-dcb9037e5bbe" : {
    "transaction" : "https://demoqa.com/Account/v1/User/0be52525-ba27-442d-b9c7-dcb9037e5bbe",
    "sampleCount" : 3,
    "errorCount" : 0,
    "errorPct" : 0.0,
    "meanResTime" : 204.0,
    "medianResTime" : 175.0,
    "minResTime" : 175.0,
    "maxResTime" : 262.0,
    "pct1ResTime" : 262.0,
    "pct2ResTime" : 262.0,
    "pct3ResTime" : 262.0,
    "throughput" : 0.024948439890892158,
    "receivedKBytesPerSec" : 0.02948821134239239,
    "sentKBytesPerSec" : 0.015998836778990087
  },
  "https://demoqa.com/books?book=9781491950296-10" : {
    "transaction" : "https://demoqa.com/books?book=9781491950296-10",
    "sampleCount" : 12,
    "errorCount" : 0,
    "errorPct" : 0.0,
    "meanResTime" : 527.5,
    "medianResTime" : 441.5,
    "minResTime" : 440.0,
    "maxResTime" : 1468.0,
    "pct1ResTime" : 1161.7000000000012,
    "pct2ResTime" : 1468.0,
    "pct3ResTime" : 1468.0,
    "throughput" : 0.05656748500961647,
    "receivedKBytesPerSec" : 3.6643144389094733,
    "sentKBytesPerSec" : 0.03202176316136818
  },
  "https://demoqa.com/books?book=9781449325862" : {
    "transaction" : "https://demoqa.com/books?book=9781449325862",
    "sampleCount" : 16,
    "errorCount" : 0,
    "errorPct" : 0.0,
    "meanResTime" : 1188.6875000000002,
    "medianResTime" : 1457.5,
    "minResTime" : 602.0,
    "maxResTime" : 1553.0,
    "pct1ResTime" : 1548.1,
    "pct2ResTime" : 1553.0,
    "pct3ResTime" : 1553.0,
    "throughput" : 0.08314236571208838,
    "receivedKBytesPerSec" : 85.40020058095728,
    "sentKBytesPerSec" : 0.48592409491740324
  },
  "https://demoqa.com/Account/v1/User/e87217b5-37cf-4a00-b253-fc928bb32e5e" : {
    "transaction" : "https://demoqa.com/Account/v1/User/e87217b5-37cf-4a00-b253-fc928bb32e5e",
    "sampleCount" : 3,
    "errorCount" : 0,
    "errorPct" : 0.0,
    "meanResTime" : 207.33333333333334,
    "medianResTime" : 181.0,
    "minResTime" : 173.0,
    "maxResTime" : 268.0,
    "pct1ResTime" : 268.0,
    "pct2ResTime" : 268.0,
    "pct3ResTime" : 268.0,
    "throughput" : 0.031744688055532044,
    "receivedKBytesPerSec" : 0.026464240270253108,
    "sentKBytesPerSec" : 0.0203571079001947
  },
  "https://demoqa.com/BookStore/v1/Books?UserId=47c8c972-c3e9-476a-8b1c-a8fa85940b7e" : {
    "transaction" : "https://demoqa.com/BookStore/v1/Books?UserId=47c8c972-c3e9-476a-8b1c-a8fa85940b7e",
    "sampleCount" : 1,
    "errorCount" : 0,
    "errorPct" : 0.0,
    "meanResTime" : 379.0,
    "medianResTime" : 379.0,
    "minResTime" : 379.0,
    "maxResTime" : 379.0,
    "pct1ResTime" : 379.0,
    "pct2ResTime" : 379.0,
    "pct3ResTime" : 379.0,
    "throughput" : 2.638522427440633,
    "receivedKBytesPerSec" : 0.47668618073878627,
    "sentKBytesPerSec" : 1.8191375329815302
  },
  "https://demoqa.com/Account/v1/User/67bba559-3eea-4cf2-b182-cd868fc17609" : {
    "transaction" : "https://demoqa.com/Account/v1/User/67bba559-3eea-4cf2-b182-cd868fc17609",
    "sampleCount" : 3,
    "errorCount" : 0,
    "errorPct" : 0.0,
    "meanResTime" : 211.33333333333334,
    "medianResTime" : 181.0,
    "minResTime" : 178.0,
    "maxResTime" : 275.0,
    "pct1ResTime" : 275.0,
    "pct2ResTime" : 275.0,
    "pct3ResTime" : 275.0,
    "throughput" : 0.021472436548949998,
    "receivedKBytesPerSec" : 0.02537969306941323,
    "sentKBytesPerSec" : 0.013769759115049315
  },
  "https://demoqa.com/Account/v1/User/e4f64d0c-3f30-4f28-9b57-3587266a087e" : {
    "transaction" : "https://demoqa.com/Account/v1/User/e4f64d0c-3f30-4f28-9b57-3587266a087e",
    "sampleCount" : 3,
    "errorCount" : 0,
    "errorPct" : 0.0,
    "meanResTime" : 204.33333333333334,
    "medianResTime" : 181.0,
    "minResTime" : 179.0,
    "maxResTime" : 253.0,
    "pct1ResTime" : 253.0,
    "pct2ResTime" : 253.0,
    "pct3ResTime" : 253.0,
    "throughput" : 0.05669791351678258,
    "receivedKBytesPerSec" : 0.03645129531108255,
    "sentKBytesPerSec" : 0.03635901355080133
  },
  "https://demoqa.com/Account/v1/User/8e2d0a61-f415-4525-8d11-e4e289ce6967" : {
    "transaction" : "https://demoqa.com/Account/v1/User/8e2d0a61-f415-4525-8d11-e4e289ce6967",
    "sampleCount" : 1,
    "errorCount" : 0,
    "errorPct" : 0.0,
    "meanResTime" : 178.0,
    "medianResTime" : 178.0,
    "minResTime" : 178.0,
    "maxResTime" : 178.0,
    "pct1ResTime" : 178.0,
    "pct2ResTime" : 178.0,
    "pct3ResTime" : 178.0,
    "throughput" : 5.617977528089887,
    "receivedKBytesPerSec" : 1.794022120786517,
    "sentKBytesPerSec" : 3.352133075842697
  },
  "https://demoqa.com/books?book=9781449337711" : {
    "transaction" : "https://demoqa.com/books?book=9781449337711",
    "sampleCount" : 17,
    "errorCount" : 0,
    "errorPct" : 0.0,
    "meanResTime" : 820.9999999999999,
    "medianResTime" : 619.0,
    "minResTime" : 607.0,
    "maxResTime" : 1550.0,
    "pct1ResTime" : 1527.6,
    "pct2ResTime" : 1550.0,
    "pct3ResTime" : 1550.0,
    "throughput" : 0.09007051991883057,
    "receivedKBytesPerSec" : 38.944256572167674,
    "sentKBytesPerSec" : 0.5476202756025452
  },
  "https://demoqa.com/Account/v1/User/923c78ab-706b-4723-bf5a-4067fa08e16f" : {
    "transaction" : "https://demoqa.com/Account/v1/User/923c78ab-706b-4723-bf5a-4067fa08e16f",
    "sampleCount" : 3,
    "errorCount" : 0,
    "errorPct" : 0.0,
    "meanResTime" : 200.33333333333334,
    "medianResTime" : 183.0,
    "minResTime" : 173.0,
    "maxResTime" : 245.0,
    "pct1ResTime" : 245.0,
    "pct2ResTime" : 245.0,
    "pct3ResTime" : 245.0,
    "throughput" : 0.07356186552890981,
    "receivedKBytesPerSec" : 0.03328482847825021,
    "sentKBytesPerSec" : 0.0471734619439949
  },
  "register" : {
    "transaction" : "register",
    "sampleCount" : 24,
    "errorCount" : 0,
    "errorPct" : 0.0,
    "meanResTime" : 757.3333333333334,
    "medianResTime" : 721.5,
    "minResTime" : 703.0,
    "maxResTime" : 1046.0,
    "pct1ResTime" : 918.0,
    "pct2ResTime" : 1020.25,
    "pct3ResTime" : 1046.0,
    "throughput" : 0.10028581457152887,
    "receivedKBytesPerSec" : 0.032514541443112874,
    "sentKBytesPerSec" : 0.045246138996138996
  },
  "https://demoqa.com/books?book=9781491904244-8" : {
    "transaction" : "https://demoqa.com/books?book=9781491904244-8",
    "sampleCount" : 14,
    "errorCount" : 0,
    "errorPct" : 0.0,
    "meanResTime" : 483.9285714285715,
    "medianResTime" : 442.0,
    "minResTime" : 148.0,
    "maxResTime" : 739.0,
    "pct1ResTime" : 737.0,
    "pct2ResTime" : 739.0,
    "pct3ResTime" : 739.0,
    "throughput" : 0.08069582860206005,
    "receivedKBytesPerSec" : 0.9469939182724175,
    "sentKBytesPerSec" : 0.044631502858937924
  },
  "https://demoqa.com/Account/v1/User/e4d9f770-b31b-4a3e-9f3b-8afeb6c88ed7" : {
    "transaction" : "https://demoqa.com/Account/v1/User/e4d9f770-b31b-4a3e-9f3b-8afeb6c88ed7",
    "sampleCount" : 1,
    "errorCount" : 0,
    "errorPct" : 0.0,
    "meanResTime" : 176.0,
    "medianResTime" : 176.0,
    "minResTime" : 176.0,
    "maxResTime" : 176.0,
    "pct1ResTime" : 176.0,
    "pct2ResTime" : 176.0,
    "pct3ResTime" : 176.0,
    "throughput" : 5.681818181818182,
    "receivedKBytesPerSec" : 1.8144087357954546,
    "sentKBytesPerSec" : 3.3902254971590913
  },
  "https://demoqa.com/books?book=9781449331818" : {
    "transaction" : "https://demoqa.com/books?book=9781449331818",
    "sampleCount" : 17,
    "errorCount" : 1,
    "errorPct" : 5.882353,
    "meanResTime" : 767.4117647058823,
    "medianResTime" : 621.0,
    "minResTime" : 605.0,
    "maxResTime" : 1525.0,
    "pct1ResTime" : 1170.5999999999997,
    "pct2ResTime" : 1525.0,
    "pct3ResTime" : 1525.0,
    "throughput" : 0.07696347404067293,
    "receivedKBytesPerSec" : 18.053045518235816,
    "sentKBytesPerSec" : 0.4743546103384582
  },
  "https://demoqa.com/books?book=9781491904244-9" : {
    "transaction" : "https://demoqa.com/books?book=9781491904244-9",
    "sampleCount" : 14,
    "errorCount" : 0,
    "errorPct" : 0.0,
    "meanResTime" : 36.785714285714285,
    "medianResTime" : 28.5,
    "minResTime" : 25.0,
    "maxResTime" : 68.0,
    "pct1ResTime" : 64.5,
    "pct2ResTime" : 68.0,
    "pct3ResTime" : 68.0,
    "throughput" : 0.08102977265360929,
    "receivedKBytesPerSec" : 0.12156726773394452,
    "sentKBytesPerSec" : 0.0433635892716581
  },
  "https://demoqa.com/BookStore/v1/Book?ISBN=9781491904244" : {
    "transaction" : "https://demoqa.com/BookStore/v1/Book?ISBN=9781491904244",
    "sampleCount" : 14,
    "errorCount" : 0,
    "errorPct" : 0.0,
    "meanResTime" : 256.57142857142856,
    "medianResTime" : 151.5,
    "minResTime" : 149.0,
    "maxResTime" : 447.0,
    "pct1ResTime" : 446.5,
    "pct2ResTime" : 447.0,
    "pct3ResTime" : 447.0,
    "throughput" : 0.08348888107008891,
    "receivedKBytesPerSec" : 0.06481802778390691,
    "sentKBytesPerSec" : 0.02967768819288317
  },
  "https://demoqa.com/books?book=9781593275846-8" : {
    "transaction" : "https://demoqa.com/books?book=9781593275846-8",
    "sampleCount" : 10,
    "errorCount" : 0,
    "errorPct" : 0.0,
    "meanResTime" : 472.0,
    "medianResTime" : 442.0,
    "minResTime" : 440.0,
    "maxResTime" : 740.0,
    "pct1ResTime" : 710.5000000000001,
    "pct2ResTime" : 740.0,
    "pct3ResTime" : 740.0,
    "throughput" : 0.05209364353361603,
    "receivedKBytesPerSec" : 0.29275203230326835,
    "sentKBytesPerSec" : 0.029317936297288006
  },
  "https://demoqa.com/books?book=9781593275846-9" : {
    "transaction" : "https://demoqa.com/books?book=9781593275846-9",
    "sampleCount" : 10,
    "errorCount" : 0,
    "errorPct" : 0.0,
    "meanResTime" : 33.900000000000006,
    "medianResTime" : 31.5,
    "minResTime" : 26.0,
    "maxResTime" : 53.0,
    "pct1ResTime" : 51.900000000000006,
    "pct2ResTime" : 53.0,
    "pct3ResTime" : 53.0,
    "throughput" : 0.05220623551276965,
    "receivedKBytesPerSec" : 0.08049141076910227,
    "sentKBytesPerSec" : 0.02793849322363063
  },
  "https://demoqa.com/books?book=9781593275846-4" : {
    "transaction" : "https://demoqa.com/books?book=9781593275846-4",
    "sampleCount" : 10,
    "errorCount" : 0,
    "errorPct" : 0.0,
    "meanResTime" : 70.39999999999999,
    "medianResTime" : 53.0,
    "minResTime" : 49.0,
    "maxResTime" : 111.0,
    "pct1ResTime" : 109.7,
    "pct2ResTime" : 111.0,
    "pct3ResTime" : 111.0,
    "throughput" : 0.05219996763602006,
    "receivedKBytesPerSec" : 7.501940778484218,
    "sentKBytesPerSec" : 0.03041769598477849
  },
  "https://demoqa.com/books?book=9781593275846-5" : {
    "transaction" : "https://demoqa.com/books?book=9781593275846-5",
    "sampleCount" : 10,
    "errorCount" : 0,
    "errorPct" : 0.0,
    "meanResTime" : 38.9,
    "medianResTime" : 36.0,
    "minResTime" : 21.0,
    "maxResTime" : 85.0,
    "pct1ResTime" : 81.20000000000002,
    "pct2ResTime" : 85.0,
    "pct3ResTime" : 85.0,
    "throughput" : 0.05220841599665866,
    "receivedKBytesPerSec" : 0.44582622265584215,
    "sentKBytesPerSec" : 0.02999944528558004
  },
  "https://demoqa.com/books?book=9781449365035" : {
    "transaction" : "https://demoqa.com/books?book=9781449365035",
    "sampleCount" : 18,
    "errorCount" : 1,
    "errorPct" : 5.5555553,
    "meanResTime" : 713.5,
    "medianResTime" : 619.0,
    "minResTime" : 605.0,
    "maxResTime" : 1535.0,
    "pct1ResTime" : 1127.3000000000006,
    "pct2ResTime" : 1535.0,
    "pct3ResTime" : 1535.0,
    "throughput" : 0.13673136085684987,
    "receivedKBytesPerSec" : 32.63388575809943,
    "sentKBytesPerSec" : 0.8393563774735082
  },
  "https://demoqa.com/books?book=9781593275846-6" : {
    "transaction" : "https://demoqa.com/books?book=9781593275846-6",
    "sampleCount" : 10,
    "errorCount" : 0,
    "errorPct" : 0.0,
    "meanResTime" : 16.3,
    "medianResTime" : 12.5,
    "minResTime" : 9.0,
    "maxResTime" : 53.0,
    "pct1ResTime" : 49.20000000000002,
    "pct2ResTime" : 53.0,
    "pct3ResTime" : 53.0,
    "throughput" : 0.0522103240694815,
    "receivedKBytesPerSec" : 0.03567535522599239,
    "sentKBytesPerSec" : 0.029898568392914018
  },
  "https://demoqa.com/books?book=9781593275846-7" : {
    "transaction" : "https://demoqa.com/books?book=9781593275846-7",
    "sampleCount" : 10,
    "errorCount" : 0,
    "errorPct" : 0.0,
    "meanResTime" : 443.5,
    "medianResTime" : 443.0,
    "minResTime" : 442.0,
    "maxResTime" : 446.0,
    "pct1ResTime" : 445.9,
    "pct2ResTime" : 446.0,
    "pct3ResTime" : 446.0,
    "throughput" : 0.052093372160260054,
    "receivedKBytesPerSec" : 0.015933246250579538,
    "sentKBytesPerSec" : 0.02942461568114689
  },
  "https://demoqa.com/books?book=9781593275846-0" : {
    "transaction" : "https://demoqa.com/books?book=9781593275846-0",
    "sampleCount" : 10,
    "errorCount" : 0,
    "errorPct" : 0.0,
    "meanResTime" : 179.8,
    "medianResTime" : 150.0,
    "minResTime" : 148.0,
    "maxResTime" : 442.0,
    "pct1ResTime" : 413.80000000000007,
    "pct2ResTime" : 442.0,
    "pct3ResTime" : 442.0,
    "throughput" : 0.052172461288033725,
    "receivedKBytesPerSec" : 0.1750630634625819,
    "sentKBytesPerSec" : 0.026188129982470054
  },
  "https://demoqa.com/books?book=9781593275846-1" : {
    "transaction" : "https://demoqa.com/books?book=9781593275846-1",
    "sampleCount" : 10,
    "errorCount" : 3,
    "errorPct" : 30.0,
    "meanResTime" : 104.59999999999998,
    "medianResTime" : 21.0,
    "minResTime" : 6.0,
    "maxResTime" : 494.0,
    "pct1ResTime" : 469.2000000000001,
    "pct2ResTime" : 494.0,
    "pct3ResTime" : 494.0,
    "throughput" : 0.05214661542392591,
    "receivedKBytesPerSec" : 0.5017380303962622,
    "sentKBytesPerSec" : 0.020919755484520276
  },
  "https://demoqa.com/books?book=9781593275846-2" : {
    "transaction" : "https://demoqa.com/books?book=9781593275846-2",
    "sampleCount" : 10,
    "errorCount" : 3,
    "errorPct" : 30.0,
    "meanResTime" : 104.4,
    "medianResTime" : 20.0,
    "minResTime" : 7.0,
    "maxResTime" : 491.0,
    "pct1ResTime" : 466.5000000000001,
    "pct2ResTime" : 491.0,
    "pct3ResTime" : 491.0,
    "throughput" : 0.052147159283498036,
    "receivedKBytesPerSec" : 1.336367714064089,
    "sentKBytesPerSec" : 0.02116950597084974
  },
  "https://demoqa.com/books?book=9781593275846-3" : {
    "transaction" : "https://demoqa.com/books?book=9781593275846-3",
    "sampleCount" : 10,
    "errorCount" : 0,
    "errorPct" : 0.0,
    "meanResTime" : 16.200000000000003,
    "medianResTime" : 12.0,
    "minResTime" : 8.0,
    "maxResTime" : 56.0,
    "pct1ResTime" : 52.100000000000016,
    "pct2ResTime" : 56.0,
    "pct3ResTime" : 56.0,
    "throughput" : 0.052210596662698665,
    "receivedKBytesPerSec" : 0.856462831602552,
    "sentKBytesPerSec" : 0.029980303552408997
  },
  "https://demoqa.com/books?book=9781593277574-7" : {
    "transaction" : "https://demoqa.com/books?book=9781593277574-7",
    "sampleCount" : 9,
    "errorCount" : 0,
    "errorPct" : 0.0,
    "meanResTime" : 410.77777777777777,
    "medianResTime" : 443.0,
    "minResTime" : 147.0,
    "maxResTime" : 449.0,
    "pct1ResTime" : 449.0,
    "pct2ResTime" : 449.0,
    "pct3ResTime" : 449.0,
    "throughput" : 0.044837687570993004,
    "receivedKBytesPerSec" : 0.011997584369582114,
    "sentKBytesPerSec" : 0.025702854105637593
  },
  "https://demoqa.com/books" : {
    "transaction" : "https://demoqa.com/books",
    "sampleCount" : 54,
    "errorCount" : 0,
    "errorPct" : 0.0,
    "meanResTime" : 1954.1666666666667,
    "medianResTime" : 1971.0,
    "minResTime" : 1518.0,
    "maxResTime" : 2394.0,
    "pct1ResTime" : 2121.5,
    "pct2ResTime" : 2184.0,
    "pct3ResTime" : 2394.0,
    "throughput" : 0.24817316972287332,
    "receivedKBytesPerSec" : 385.2231179842249,
    "sentKBytesPerSec" : 1.3838562491382875
  },
  "https://demoqa.com/books?book=9781593277574-6" : {
    "transaction" : "https://demoqa.com/books?book=9781593277574-6",
    "sampleCount" : 9,
    "errorCount" : 0,
    "errorPct" : 0.0,
    "meanResTime" : 12.0,
    "medianResTime" : 11.0,
    "minResTime" : 10.0,
    "maxResTime" : 16.0,
    "pct1ResTime" : 16.0,
    "pct2ResTime" : 16.0,
    "pct3ResTime" : 16.0,
    "throughput" : 0.044934620127714174,
    "receivedKBytesPerSec" : 0.027299146928718716,
    "sentKBytesPerSec" : 0.026109471656240172
  },
  "https://demoqa.com/books?book=9781593277574-9" : {
    "transaction" : "https://demoqa.com/books?book=9781593277574-9",
    "sampleCount" : 9,
    "errorCount" : 0,
    "errorPct" : 0.0,
    "meanResTime" : 32.77777777777778,
    "medianResTime" : 27.0,
    "minResTime" : 26.0,
    "maxResTime" : 51.0,
    "pct1ResTime" : 51.0,
    "pct2ResTime" : 51.0,
    "pct3ResTime" : 51.0,
    "throughput" : 0.04493304975586376,
    "receivedKBytesPerSec" : 0.06456200573645268,
    "sentKBytesPerSec" : 0.024046202408411467
  },
  "https://demoqa.com/Account/v1/User" : {
    "transaction" : "https://demoqa.com/Account/v1/User",
    "sampleCount" : 24,
    "errorCount" : 0,
    "errorPct" : 0.0,
    "meanResTime" : 757.3333333333334,
    "medianResTime" : 721.5,
    "minResTime" : 703.0,
    "maxResTime" : 1046.0,
    "pct1ResTime" : 918.0,
    "pct2ResTime" : 1020.25,
    "pct3ResTime" : 1046.0,
    "throughput" : 0.09859461591234939,
    "receivedKBytesPerSec" : 0.03196622312783203,
    "sentKBytesPerSec" : 0.04448311772607951
  },
  "https://demoqa.com/books?book=9781593277574-8" : {
    "transaction" : "https://demoqa.com/books?book=9781593277574-8",
    "sampleCount" : 9,
    "errorCount" : 0,
    "errorPct" : 0.0,
    "meanResTime" : 378.3333333333333,
    "medianResTime" : 442.0,
    "minResTime" : 148.0,
    "maxResTime" : 455.0,
    "pct1ResTime" : 455.0,
    "pct2ResTime" : 455.0,
    "pct3ResTime" : 455.0,
    "throughput" : 0.044837910951908845,
    "receivedKBytesPerSec" : 0.012041431163842709,
    "sentKBytesPerSec" : 0.025615408112174488
  },
  "https://demoqa.com/books?book=9781593277574-3" : {
    "transaction" : "https://demoqa.com/books?book=9781593277574-3",
    "sampleCount" : 9,
    "errorCount" : 0,
    "errorPct" : 0.0,
    "meanResTime" : 12.222222222222221,
    "medianResTime" : 11.0,
    "minResTime" : 9.0,
    "maxResTime" : 17.0,
    "pct1ResTime" : 17.0,
    "pct2ResTime" : 17.0,
    "pct3ResTime" : 17.0,
    "throughput" : 0.04493394709776628,
    "receivedKBytesPerSec" : 0.036903759286349064,
    "sentKBytesPerSec" : 0.02627972817458336
  },
  "https://demoqa.com/books?book=9781593277574-2" : {
    "transaction" : "https://demoqa.com/books?book=9781593277574-2",
    "sampleCount" : 9,
    "errorCount" : 1,
    "errorPct" : 11.111111,
    "meanResTime" : 27.444444444444443,
    "medianResTime" : 20.0,
    "minResTime" : 8.0,
    "maxResTime" : 81.0,
    "pct1ResTime" : 81.0,
    "pct2ResTime" : 81.0,
    "pct3ResTime" : 81.0,
    "throughput" : 0.044932601098352475,
    "receivedKBytesPerSec" : 0.023538910384423364,
    "sentKBytesPerSec" : 0.023392645406889664
  },
  "https://demoqa.com/books?book=9781593277574-5" : {
    "transaction" : "https://demoqa.com/books?book=9781593277574-5",
    "sampleCount" : 9,
    "errorCount" : 0,
    "errorPct" : 0.0,
    "meanResTime" : 36.44444444444444,
    "medianResTime" : 38.0,
    "minResTime" : 21.0,
    "maxResTime" : 51.0,
    "pct1ResTime" : 51.0,
    "pct2ResTime" : 51.0,
    "pct3ResTime" : 51.0,
    "throughput" : 0.04493035794518496,
    "receivedKBytesPerSec" : 0.4238401181293994,
    "sentKBytesPerSec" : 0.02579497872048325
  },
  "https://demoqa.com/books?book=9781593277574-4" : {
    "transaction" : "https://demoqa.com/books?book=9781593277574-4",
    "sampleCount" : 9,
    "errorCount" : 0,
    "errorPct" : 0.0,
    "meanResTime" : 87.44444444444444,
    "medianResTime" : 60.0,
    "minResTime" : 50.0,
    "maxResTime" : 192.0,
    "pct1ResTime" : 192.0,
    "pct2ResTime" : 192.0,
    "pct3ResTime" : 192.0,
    "throughput" : 0.044923181359874616,
    "receivedKBytesPerSec" : 6.463332467106248,
    "sentKBytesPerSec" : 0.026341674486627865
  },
  "https://demoqa.com/Account/v1/User/a4c59c5a-ed71-4df6-a9fe-79d0e54f7c7a" : {
    "transaction" : "https://demoqa.com/Account/v1/User/a4c59c5a-ed71-4df6-a9fe-79d0e54f7c7a",
    "sampleCount" : 2,
    "errorCount" : 0,
    "errorPct" : 0.0,
    "meanResTime" : 176.0,
    "medianResTime" : 176.0,
    "minResTime" : 175.0,
    "maxResTime" : 177.0,
    "pct1ResTime" : 177.0,
    "pct2ResTime" : 177.0,
    "pct3ResTime" : 177.0,
    "throughput" : 0.04445728766087981,
    "receivedKBytesPerSec" : 0.039290864583101784,
    "sentKBytesPerSec" : 0.02763385116811523
  },
  "https://demoqa.com/books?book=9781491904244-2" : {
    "transaction" : "https://demoqa.com/books?book=9781491904244-2",
    "sampleCount" : 14,
    "errorCount" : 0,
    "errorPct" : 0.0,
    "meanResTime" : 21.714285714285715,
    "medianResTime" : 21.0,
    "minResTime" : 6.0,
    "maxResTime" : 36.0,
    "pct1ResTime" : 34.5,
    "pct2ResTime" : 36.0,
    "pct3ResTime" : 36.0,
    "throughput" : 0.0810241451952682,
    "receivedKBytesPerSec" : 4.324392463597008,
    "sentKBytesPerSec" : 0.04481308923362733
  },
  "https://demoqa.com/books?book=9781491904244-3" : {
    "transaction" : "https://demoqa.com/books?book=9781491904244-3",
    "sampleCount" : 14,
    "errorCount" : 0,
    "errorPct" : 0.0,
    "meanResTime" : 19.42857142857143,
    "medianResTime" : 12.0,
    "minResTime" : 9.0,
    "maxResTime" : 43.0,
    "pct1ResTime" : 39.0,
    "pct2ResTime" : 43.0,
    "pct3ResTime" : 43.0,
    "throughput" : 0.08102836571574092,
    "receivedKBytesPerSec" : 2.774441537310669,
    "sentKBytesPerSec" : 0.04757364357068857
  },
  "https://demoqa.com/books?book=9781593277574-1" : {
    "transaction" : "https://demoqa.com/books?book=9781593277574-1",
    "sampleCount" : 9,
    "errorCount" : 1,
    "errorPct" : 11.111111,
    "meanResTime" : 27.888888888888893,
    "medianResTime" : 21.0,
    "minResTime" : 8.0,
    "maxResTime" : 90.0,
    "pct1ResTime" : 90.0,
    "pct2ResTime" : 90.0,
    "pct3ResTime" : 90.0,
    "throughput" : 0.044931479493772,
    "receivedKBytesPerSec" : 0.02353832280771823,
    "sentKBytesPerSec" : 0.02311904033848381
  },
  "https://demoqa.com/books?book=9781491904244-0" : {
    "transaction" : "https://demoqa.com/books?book=9781491904244-0",
    "sampleCount" : 14,
    "errorCount" : 0,
    "errorPct" : 0.0,
    "meanResTime" : 170.28571428571428,
    "medianResTime" : 149.0,
    "minResTime" : 148.0,
    "maxResTime" : 444.0,
    "pct1ResTime" : 297.5,
    "pct2ResTime" : 444.0,
    "pct3ResTime" : 444.0,
    "throughput" : 0.08096885012665841,
    "receivedKBytesPerSec" : 0.27168844632343586,
    "sentKBytesPerSec" : 0.04064256734873284
  },
  "https://demoqa.com/books?book=9781593277574-0" : {
    "transaction" : "https://demoqa.com/books?book=9781593277574-0",
    "sampleCount" : 9,
    "errorCount" : 0,
    "errorPct" : 0.0,
    "meanResTime" : 182.55555555555554,
    "medianResTime" : 150.0,
    "minResTime" : 149.0,
    "maxResTime" : 446.0,
    "pct1ResTime" : 446.0,
    "pct2ResTime" : 446.0,
    "pct3ResTime" : 446.0,
    "throughput" : 0.044836123966900975,
    "receivedKBytesPerSec" : 0.15044621284206228,
    "sentKBytesPerSec" : 0.022505632538073344
  },
  "https://demoqa.com/books?book=9781491904244-1" : {
    "transaction" : "https://demoqa.com/books?book=9781491904244-1",
    "sampleCount" : 14,
    "errorCount" : 0,
    "errorPct" : 0.0,
    "meanResTime" : 21.71428571428571,
    "medianResTime" : 21.0,
    "minResTime" : 7.0,
    "maxResTime" : 39.0,
    "pct1ResTime" : 34.5,
    "pct2ResTime" : 39.0,
    "pct3ResTime" : 39.0,
    "throughput" : 0.08102977265360929,
    "receivedKBytesPerSec" : 1.5456304785531554,
    "sentKBytesPerSec" : 0.04426228722449877
  },
  "https://demoqa.com/BookStore/v1/Book?ISBN=9781593277574" : {
    "transaction" : "https://demoqa.com/BookStore/v1/Book?ISBN=9781593277574",
    "sampleCount" : 9,
    "errorCount" : 0,
    "errorPct" : 0.0,
    "meanResTime" : 152.66666666666666,
    "medianResTime" : 152.0,
    "minResTime" : 150.0,
    "maxResTime" : 159.0,
    "pct1ResTime" : 159.0,
    "pct2ResTime" : 159.0,
    "pct3ResTime" : 159.0,
    "throughput" : 0.04322289084299045,
    "receivedKBytesPerSec" : 0.034021142597119435,
    "sentKBytesPerSec" : 0.01536438697934426
  },
  "https://demoqa.com/books?book=9781491904244-6" : {
    "transaction" : "https://demoqa.com/books?book=9781491904244-6",
    "sampleCount" : 14,
    "errorCount" : 0,
    "errorPct" : 0.0,
    "meanResTime" : 19.71428571428571,
    "medianResTime" : 15.5,
    "minResTime" : 9.0,
    "maxResTime" : 37.0,
    "pct1ResTime" : 37.0,
    "pct2ResTime" : 37.0,
    "pct3ResTime" : 37.0,
    "throughput" : 0.08102789674730872,
    "receivedKBytesPerSec" : 0.06265870977543697,
    "sentKBytesPerSec" : 0.045623408380599605
  },
  "deleteAccount" : {
    "transaction" : "deleteAccount",
    "sampleCount" : 14,
    "errorCount" : 0,
    "errorPct" : 0.0,
    "meanResTime" : 321.0,
    "medianResTime" : 262.0,
    "minResTime" : 245.0,
    "maxResTime" : 590.0,
    "pct1ResTime" : 572.5,
    "pct2ResTime" : 590.0,
    "pct3ResTime" : 590.0,
    "throughput" : 0.08766437069505321,
    "receivedKBytesPerSec" : 0.015837801346274265,
    "sentKBytesPerSec" : 0.05966998669380088
  },
  "https://demoqa.com/books?book=9781449325862-10" : {
    "transaction" : "https://demoqa.com/books?book=9781449325862-10",
    "sampleCount" : 16,
    "errorCount" : 0,
    "errorPct" : 0.0,
    "meanResTime" : 975.25,
    "medianResTime" : 1249.5,
    "minResTime" : 440.0,
    "maxResTime" : 1332.0,
    "pct1ResTime" : 1330.6,
    "pct2ResTime" : 1332.0,
    "pct3ResTime" : 1332.0,
    "throughput" : 0.08323882258685451,
    "receivedKBytesPerSec" : 40.294347189779316,
    "sentKBytesPerSec" : 0.04324516954707676
  },
  "https://demoqa.com/books?book=9781491904244-7" : {
    "transaction" : "https://demoqa.com/books?book=9781491904244-7",
    "sampleCount" : 14,
    "errorCount" : 0,
    "errorPct" : 0.0,
    "meanResTime" : 421.5714285714285,
    "medianResTime" : 442.5,
    "minResTime" : 149.0,
    "maxResTime" : 445.0,
    "pct1ResTime" : 444.5,
    "pct2ResTime" : 445.0,
    "pct3ResTime" : 445.0,
    "throughput" : 0.08082907537311279,
    "receivedKBytesPerSec" : 0.028258602523021852,
    "sentKBytesPerSec" : 0.044879983256834385
  },
  "https://demoqa.com/books?book=9781491904244-4" : {
    "transaction" : "https://demoqa.com/books?book=9781491904244-4",
    "sampleCount" : 14,
    "errorCount" : 0,
    "errorPct" : 0.0,
    "meanResTime" : 73.35714285714286,
    "medianResTime" : 76.0,
    "minResTime" : 51.0,
    "maxResTime" : 110.0,
    "pct1ResTime" : 100.0,
    "pct2ResTime" : 110.0,
    "pct3ResTime" : 110.0,
    "throughput" : 0.08101804966406445,
    "receivedKBytesPerSec" : 11.646344639209264,
    "sentKBytesPerSec" : 0.04687811955659979
  },
  "https://demoqa.com/Account/v1/GenerateToken" : {
    "transaction" : "https://demoqa.com/Account/v1/GenerateToken",
    "sampleCount" : 23,
    "errorCount" : 0,
    "errorPct" : 0.0,
    "meanResTime" : 420.69565217391306,
    "medianResTime" : 396.0,
    "minResTime" : 369.0,
    "maxResTime" : 650.0,
    "pct1ResTime" : 527.4,
    "pct2ResTime" : 625.7999999999996,
    "pct3ResTime" : 650.0,
    "throughput" : 0.1031251401156795,
    "receivedKBytesPerSec" : 0.05337531666143568,
    "sentKBytesPerSec" : 0.047433536127426804
  },
  "https://demoqa.com/books?book=9781491904244-5" : {
    "transaction" : "https://demoqa.com/books?book=9781491904244-5",
    "sampleCount" : 14,
    "errorCount" : 0,
    "errorPct" : 0.0,
    "meanResTime" : 49.07142857142857,
    "medianResTime" : 50.5,
    "minResTime" : 20.0,
    "maxResTime" : 78.0,
    "pct1ResTime" : 76.0,
    "pct2ResTime" : 78.0,
    "pct3ResTime" : 78.0,
    "throughput" : 0.08100914246036338,
    "receivedKBytesPerSec" : 4.237807717205763,
    "sentKBytesPerSec" : 0.04321128016143965
  },
  "https://demoqa.com/books?book=9781593277574" : {
    "transaction" : "https://demoqa.com/books?book=9781593277574",
    "sampleCount" : 9,
    "errorCount" : 1,
    "errorPct" : 11.111111,
    "meanResTime" : 655.0,
    "medianResTime" : 616.0,
    "minResTime" : 610.0,
    "maxResTime" : 919.0,
    "pct1ResTime" : 919.0,
    "pct2ResTime" : 919.0,
    "pct3ResTime" : 919.0,
    "throughput" : 0.04473249965208056,
    "receivedKBytesPerSec" : 7.2190663115817415,
    "sentKBytesPerSec" : 0.27360311120747927
  },
  "https://demoqa.com/BookStore/v1/Books?UserId=0be52525-ba27-442d-b9c7-dcb9037e5bbe" : {
    "transaction" : "https://demoqa.com/BookStore/v1/Books?UserId=0be52525-ba27-442d-b9c7-dcb9037e5bbe",
    "sampleCount" : 1,
    "errorCount" : 0,
    "errorPct" : 0.0,
    "meanResTime" : 255.0,
    "medianResTime" : 255.0,
    "minResTime" : 255.0,
    "maxResTime" : 255.0,
    "pct1ResTime" : 255.0,
    "pct2ResTime" : 255.0,
    "pct3ResTime" : 255.0,
    "throughput" : 3.9215686274509802,
    "receivedKBytesPerSec" : 0.7084865196078431,
    "sentKBytesPerSec" : 2.703737745098039
  },
  "https://demoqa.com/Account/v1/User/ced950c7-0116-499e-b920-1a67e8fa6c0b" : {
    "transaction" : "https://demoqa.com/Account/v1/User/ced950c7-0116-499e-b920-1a67e8fa6c0b",
    "sampleCount" : 3,
    "errorCount" : 0,
    "errorPct" : 0.0,
    "meanResTime" : 202.33333333333334,
    "medianResTime" : 178.0,
    "minResTime" : 176.0,
    "maxResTime" : 253.0,
    "pct1ResTime" : 253.0,
    "pct2ResTime" : 253.0,
    "pct3ResTime" : 253.0,
    "throughput" : 0.04273260782861375,
    "receivedKBytesPerSec" : 0.027083459453877273,
    "sentKBytesPerSec" : 0.027403397598427442
  },
  "https://demoqa.com/Account/v1/User/9bac8680-a15f-4575-ad14-4d4285a93f62" : {
    "transaction" : "https://demoqa.com/Account/v1/User/9bac8680-a15f-4575-ad14-4d4285a93f62",
    "sampleCount" : 3,
    "errorCount" : 0,
    "errorPct" : 0.0,
    "meanResTime" : 204.0,
    "medianResTime" : 182.0,
    "minResTime" : 180.0,
    "maxResTime" : 250.0,
    "pct1ResTime" : 250.0,
    "pct2ResTime" : 250.0,
    "pct3ResTime" : 250.0,
    "throughput" : 0.020276572448193357,
    "receivedKBytesPerSec" : 0.02795289203063114,
    "sentKBytesPerSec" : 0.013002880118144829
  },
  "addBook" : {
    "transaction" : "addBook",
    "sampleCount" : 59,
    "errorCount" : 1,
    "errorPct" : 1.6949153,
    "meanResTime" : 1522.9661016949153,
    "medianResTime" : 1401.0,
    "minResTime" : 1092.0,
    "maxResTime" : 2143.0,
    "pct1ResTime" : 2036.0,
    "pct2ResTime" : 2043.0,
    "pct3ResTime" : 2143.0,
    "throughput" : 0.26738937331182133,
    "receivedKBytesPerSec" : 174.51839109208166,
    "sentKBytesPerSec" : 1.9851899498418326
  },
  "https://demoqa.com/books-0" : {
    "transaction" : "https://demoqa.com/books-0",
    "sampleCount" : 54,
    "errorCount" : 0,
    "errorPct" : 0.0,
    "meanResTime" : 600.5185185185184,
    "medianResTime" : 598.0,
    "minResTime" : 593.0,
    "maxResTime" : 668.0,
    "pct1ResTime" : 605.0,
    "pct2ResTime" : 625.0,
    "pct3ResTime" : 668.0,
    "throughput" : 0.24976642214225583,
    "receivedKBytesPerSec" : 0.8380834242976476,
    "sentKBytesPerSec" : 0.12073669820353189
  },
  "https://demoqa.com/books-3" : {
    "transaction" : "https://demoqa.com/books-3",
    "sampleCount" : 54,
    "errorCount" : 0,
    "errorPct" : 0.0,
    "meanResTime" : 51.33333333333333,
    "medianResTime" : 48.5,
    "minResTime" : 20.0,
    "maxResTime" : 231.0,
    "pct1ResTime" : 71.5,
    "pct2ResTime" : 101.25,
    "pct3ResTime" : 231.0,
    "throughput" : 0.25051262305272826,
    "receivedKBytesPerSec" : 39.25542679493454,
    "sentKBytesPerSec" : 0.13284018976331197
  },
  "https://demoqa.com/books-4" : {
    "transaction" : "https://demoqa.com/books-4",
    "sampleCount" : 54,
    "errorCount" : 0,
    "errorPct" : 0.0,
    "meanResTime" : 104.46296296296299,
    "medianResTime" : 101.0,
    "minResTime" : 56.0,
    "maxResTime" : 227.0,
    "pct1ResTime" : 144.5,
    "pct2ResTime" : 210.0,
    "pct3ResTime" : 227.0,
    "throughput" : 0.2504719540986952,
    "receivedKBytesPerSec" : 36.00218170058861,
    "sentKBytesPerSec" : 0.13795525596842198
  },
  "https://demoqa.com/books-1" : {
    "transaction" : "https://demoqa.com/books-1",
    "sampleCount" : 54,
    "errorCount" : 0,
    "errorPct" : 0.0,
    "meanResTime" : 38.111111111111114,
    "medianResTime" : 34.0,
    "minResTime" : 13.0,
    "maxResTime" : 138.0,
    "pct1ResTime" : 53.0,
    "pct2ResTime" : 66.5,
    "pct3ResTime" : 138.0,
    "throughput" : 0.25052540745173907,
    "receivedKBytesPerSec" : 22.00586799224763,
    "sentKBytesPerSec" : 0.1257520111622987
  },
  "https://demoqa.com/books?book=9781491904244-10" : {
    "transaction" : "https://demoqa.com/books?book=9781491904244-10",
    "sampleCount" : 14,
    "errorCount" : 0,
    "errorPct" : 0.0,
    "meanResTime" : 609.0714285714287,
    "medianResTime" : 441.0,
    "minResTime" : 148.0,
    "maxResTime" : 1323.0,
    "pct1ResTime" : 1323.0,
    "pct2ResTime" : 1323.0,
    "pct3ResTime" : 1323.0,
    "throughput" : 0.08042833835052968,
    "receivedKBytesPerSec" : 13.362992255540938,
    "sentKBytesPerSec" : 0.04462381440011949
  },
  "https://demoqa.com/books-2" : {
    "transaction" : "https://demoqa.com/books-2",
    "sampleCount" : 54,
    "errorCount" : 0,
    "errorPct" : 0.0,
    "meanResTime" : 42.37037037037036,
    "medianResTime" : 38.0,
    "minResTime" : 17.0,
    "maxResTime" : 222.0,
    "pct1ResTime" : 52.0,
    "pct2ResTime" : 73.25,
    "pct3ResTime" : 222.0,
    "throughput" : 0.2505277320281148,
    "receivedKBytesPerSec" : 62.10347607228189,
    "sentKBytesPerSec" : 0.12746576990883576
  },
  "https://demoqa.com/BookStore/v1/Book?ISBN=9781449365035" : {
    "transaction" : "https://demoqa.com/BookStore/v1/Book?ISBN=9781449365035",
    "sampleCount" : 18,
    "errorCount" : 0,
    "errorPct" : 0.0,
    "meanResTime" : 200.44444444444446,
    "medianResTime" : 152.0,
    "minResTime" : 150.0,
    "maxResTime" : 446.0,
    "pct1ResTime" : 444.2,
    "pct2ResTime" : 446.0,
    "pct3ResTime" : 446.0,
    "throughput" : 0.1317282008123239,
    "receivedKBytesPerSec" : 0.09841022814592557,
    "sentKBytesPerSec" : 0.04682525888250576
  },
  "https://demoqa.com/books-7" : {
    "transaction" : "https://demoqa.com/books-7",
    "sampleCount" : 54,
    "errorCount" : 0,
    "errorPct" : 0.0,
    "meanResTime" : 412.68518518518516,
    "medianResTime" : 443.0,
    "minResTime" : 148.0,
    "maxResTime" : 619.0,
    "pct1ResTime" : 455.0,
    "pct2ResTime" : 605.5,
    "pct3ResTime" : 619.0,
    "throughput" : 0.25020502912108533,
    "receivedKBytesPerSec" : 0.16273100526820589,
    "sentKBytesPerSec" : 0.122414765224281
  },
  "https://demoqa.com/books-8" : {
    "transaction" : "https://demoqa.com/books-8",
    "sampleCount" : 54,
    "errorCount" : 0,
    "errorPct" : 0.0,
    "meanResTime" : 739.7962962962964,
    "medianResTime" : 736.0,
    "minResTime" : 452.0,
    "maxResTime" : 904.0,
    "pct1ResTime" : 741.5,
    "pct2ResTime" : 898.75,
    "pct3ResTime" : 904.0,
    "throughput" : 0.24985309563358582,
    "receivedKBytesPerSec" : 13.437167802380081,
    "sentKBytesPerSec" : 0.12151058752492747
  },
  "https://demoqa.com/BookStore/v1/Books" : {
    "transaction" : "https://demoqa.com/BookStore/v1/Books",
    "sampleCount" : 172,
    "errorCount" : 0,
    "errorPct" : 0.0,
    "meanResTime" : 183.39534883720938,
    "medianResTime" : 153.0,
    "minResTime" : 149.0,
    "maxResTime" : 504.0,
    "pct1ResTime" : 197.0,
    "pct2ResTime" : 445.35,
    "pct3ResTime" : 488.6700000000002,
    "throughput" : 0.7285758460163422,
    "receivedKBytesPerSec" : 1.557746188214015,
    "sentKBytesPerSec" : 0.35259781501374554
  },
  "https://demoqa.com/BookStore/v1/Book?ISBN=9781593275846" : {
    "transaction" : "https://demoqa.com/BookStore/v1/Book?ISBN=9781593275846",
    "sampleCount" : 10,
    "errorCount" : 0,
    "errorPct" : 0.0,
    "meanResTime" : 181.39999999999998,
    "medianResTime" : 151.5,
    "minResTime" : 149.0,
    "maxResTime" : 443.0,
    "pct1ResTime" : 414.7000000000001,
    "pct2ResTime" : 443.0,
    "pct3ResTime" : 443.0,
    "throughput" : 0.0527520757941825,
    "receivedKBytesPerSec" : 0.040851949321080785,
    "sentKBytesPerSec" : 0.01875171444246331
  },
  "https://demoqa.com/books-5" : {
    "transaction" : "https://demoqa.com/books-5",
    "sampleCount" : 54,
    "errorCount" : 0,
    "errorPct" : 0.0,
    "meanResTime" : 82.12962962962966,
    "medianResTime" : 76.5,
    "minResTime" : 46.0,
    "maxResTime" : 163.0,
    "pct1ResTime" : 120.5,
    "pct2ResTime" : 133.5,
    "pct3ResTime" : 163.0,
    "throughput" : 0.2504754394916276,
    "receivedKBytesPerSec" : 20.308282829966604,
    "sentKBytesPerSec" : 0.12670534927408506
  },
  "https://demoqa.com/books-6" : {
    "transaction" : "https://demoqa.com/books-6",
    "sampleCount" : 54,
    "errorCount" : 0,
    "errorPct" : 0.0,
    "meanResTime" : 46.00000000000001,
    "medianResTime" : 46.0,
    "minResTime" : 16.0,
    "maxResTime" : 93.0,
    "pct1ResTime" : 68.5,
    "pct2ResTime" : 74.5,
    "pct3ResTime" : 93.0,
    "throughput" : 0.25057888362466996,
    "receivedKBytesPerSec" : 0.3468887977898014,
    "sentKBytesPerSec" : 0.12455532398921583
  },
  "https://demoqa.com/Account/v1/User/02890277-743b-4466-8bcc-16dfd3bcdd9d" : {
    "transaction" : "https://demoqa.com/Account/v1/User/02890277-743b-4466-8bcc-16dfd3bcdd9d",
    "sampleCount" : 3,
    "errorCount" : 0,
    "errorPct" : 0.0,
    "meanResTime" : 317.0,
    "medianResTime" : 184.0,
    "minResTime" : 177.0,
    "maxResTime" : 590.0,
    "pct1ResTime" : 590.0,
    "pct2ResTime" : 590.0,
    "pct3ResTime" : 590.0,
    "throughput" : 0.025180882673873993,
    "receivedKBytesPerSec" : 0.02525465479108261,
    "sentKBytesPerSec" : 0.016147896766774663
  },
  "https://demoqa.com/Account/v1/User/f3109fe0-c750-44b6-afb5-36cfc513d103" : {
    "transaction" : "https://demoqa.com/Account/v1/User/f3109fe0-c750-44b6-afb5-36cfc513d103",
    "sampleCount" : 1,
    "errorCount" : 0,
    "errorPct" : 0.0,
    "meanResTime" : 175.0,
    "medianResTime" : 175.0,
    "minResTime" : 175.0,
    "maxResTime" : 175.0,
    "pct1ResTime" : 175.0,
    "pct2ResTime" : 175.0,
    "pct3ResTime" : 175.0,
    "throughput" : 5.714285714285714,
    "receivedKBytesPerSec" : 1.8247767857142858,
    "sentKBytesPerSec" : 3.4095982142857144
  },
  "https://demoqa.com/books-9" : {
    "transaction" : "https://demoqa.com/books-9",
    "sampleCount" : 54,
    "errorCount" : 0,
    "errorPct" : 0.0,
    "meanResTime" : 35.629629629629626,
    "medianResTime" : 29.5,
    "minResTime" : 22.0,
    "maxResTime" : 70.0,
    "pct1ResTime" : 55.0,
    "pct2ResTime" : 59.5,
    "pct3ResTime" : 70.0,
    "throughput" : 0.2506905596434623,
    "receivedKBytesPerSec" : 0.3635774761495787,
    "sentKBytesPerSec" : 0.13415861980919663
  },
  "https://demoqa.com/BookStore/v1/Book?ISBN=9781449337711" : {
    "transaction" : "https://demoqa.com/BookStore/v1/Book?ISBN=9781449337711",
    "sampleCount" : 17,
    "errorCount" : 0,
    "errorPct" : 0.0,
    "meanResTime" : 152.7058823529412,
    "medianResTime" : 152.0,
    "minResTime" : 149.0,
    "maxResTime" : 163.0,
    "pct1ResTime" : 159.0,
    "pct2ResTime" : 163.0,
    "pct3ResTime" : 163.0,
    "throughput" : 0.09170748548863907,
    "receivedKBytesPerSec" : 0.07442277386822173,
    "sentKBytesPerSec" : 0.03259914523228966
  },
  "https://demoqa.com/BookStore/v1/Books?UserId=bbe48237-e997-45ee-a696-457dd520fc5e" : {
    "transaction" : "https://demoqa.com/BookStore/v1/Books?UserId=bbe48237-e997-45ee-a696-457dd520fc5e",
    "sampleCount" : 1,
    "errorCount" : 0,
    "errorPct" : 0.0,
    "meanResTime" : 184.0,
    "medianResTime" : 184.0,
    "minResTime" : 184.0,
    "maxResTime" : 184.0,
    "pct1ResTime" : 184.0,
    "pct2ResTime" : 184.0,
    "pct3ResTime" : 184.0,
    "throughput" : 5.434782608695652,
    "receivedKBytesPerSec" : 0.9818699048913043,
    "sentKBytesPerSec" : 3.7470278532608696
  },
  "https://demoqa.com/books?book=9781593275846-10" : {
    "transaction" : "https://demoqa.com/books?book=9781593275846-10",
    "sampleCount" : 10,
    "errorCount" : 0,
    "errorPct" : 0.0,
    "meanResTime" : 499.79999999999995,
    "medianResTime" : 441.5,
    "minResTime" : 147.0,
    "maxResTime" : 1319.0,
    "pct1ResTime" : 1231.4000000000003,
    "pct2ResTime" : 1319.0,
    "pct3ResTime" : 1319.0,
    "throughput" : 0.052086860047815736,
    "receivedKBytesPerSec" : 4.046075751548282,
    "sentKBytesPerSec" : 0.02941076414028033
  },
  "https://demoqa.com/Account/v1/User/59d17239-7489-45f1-abe3-02f9500dab7d" : {
    "transaction" : "https://demoqa.com/Account/v1/User/59d17239-7489-45f1-abe3-02f9500dab7d",
    "sampleCount" : 3,
    "errorCount" : 0,
    "errorPct" : 0.0,
    "meanResTime" : 208.66666666666666,
    "medianResTime" : 184.0,
    "minResTime" : 180.0,
    "maxResTime" : 262.0,
    "pct1ResTime" : 262.0,
    "pct2ResTime" : 262.0,
    "pct3ResTime" : 262.0,
    "throughput" : 0.01769128704113224,
    "receivedKBytesPerSec" : 0.02438886738906089,
    "sentKBytesPerSec" : 0.011344998525726081
  },
  "https://demoqa.com/books?book=9781593275846" : {
    "transaction" : "https://demoqa.com/books?book=9781593275846",
    "sampleCount" : 10,
    "errorCount" : 3,
    "errorPct" : 30.0,
    "meanResTime" : 743.5,
    "medianResTime" : 629.0,
    "minResTime" : 608.0,
    "maxResTime" : 1525.0,
    "pct1ResTime" : 1462.2000000000003,
    "pct2ResTime" : 1525.0,
    "pct3ResTime" : 1525.0,
    "throughput" : 0.052039154259664974,
    "receivedKBytesPerSec" : 15.252305131255756,
    "sentKBytesPerSec" : 0.30394626729651386
  },
  "https://demoqa.com/BookStore/v1/Books?UserId=9bac8680-a15f-4575-ad14-4d4285a93f62" : {
    "transaction" : "https://demoqa.com/BookStore/v1/Books?UserId=9bac8680-a15f-4575-ad14-4d4285a93f62",
    "sampleCount" : 1,
    "errorCount" : 0,
    "errorPct" : 0.0,
    "meanResTime" : 253.0,
    "medianResTime" : 253.0,
    "minResTime" : 253.0,
    "maxResTime" : 253.0,
    "pct1ResTime" : 253.0,
    "pct2ResTime" : 253.0,
    "pct3ResTime" : 253.0,
    "throughput" : 3.952569169960474,
    "receivedKBytesPerSec" : 0.7140872035573123,
    "sentKBytesPerSec" : 2.7251111660079053
  },
  "https://demoqa.com/BookStore/v1/Books?UserId=67bba559-3eea-4cf2-b182-cd868fc17609" : {
    "transaction" : "https://demoqa.com/BookStore/v1/Books?UserId=67bba559-3eea-4cf2-b182-cd868fc17609",
    "sampleCount" : 1,
    "errorCount" : 0,
    "errorPct" : 0.0,
    "meanResTime" : 261.0,
    "medianResTime" : 261.0,
    "minResTime" : 261.0,
    "maxResTime" : 261.0,
    "pct1ResTime" : 261.0,
    "pct2ResTime" : 261.0,
    "pct3ResTime" : 261.0,
    "throughput" : 3.8314176245210727,
    "receivedKBytesPerSec" : 0.6921994731800766,
    "sentKBytesPerSec" : 2.6415828544061304
  },
  "https://demoqa.com/books?book=9781491904244" : {
    "transaction" : "https://demoqa.com/books?book=9781491904244",
    "sampleCount" : 14,
    "errorCount" : 0,
    "errorPct" : 0.0,
    "meanResTime" : 828.5714285714286,
    "medianResTime" : 621.0,
    "minResTime" : 604.0,
    "maxResTime" : 1518.0,
    "pct1ResTime" : 1514.5,
    "pct2ResTime" : 1518.0,
    "pct3ResTime" : 1518.0,
    "throughput" : 0.08033649514824952,
    "receivedKBytesPerSec" : 39.0926542048265,
    "sentKBytesPerSec" : 0.4869839635444462
  },
  "https://demoqa.com/Account/v1/User/f7739bb3-3bbc-4e68-989a-965502abfa4d" : {
    "transaction" : "https://demoqa.com/Account/v1/User/f7739bb3-3bbc-4e68-989a-965502abfa4d",
    "sampleCount" : 2,
    "errorCount" : 0,
    "errorPct" : 0.0,
    "meanResTime" : 179.5,
    "medianResTime" : 179.5,
    "minResTime" : 177.0,
    "maxResTime" : 182.0,
    "pct1ResTime" : 182.0,
    "pct2ResTime" : 182.0,
    "pct3ResTime" : 182.0,
    "throughput" : 0.041841004184100423,
    "receivedKBytesPerSec" : 0.03605926385983264,
    "sentKBytesPerSec" : 0.026007616370292887
  },
  "https://demoqa.com/books?book=9781593277574-10" : {
    "transaction" : "https://demoqa.com/books?book=9781593277574-10",
    "sampleCount" : 9,
    "errorCount" : 0,
    "errorPct" : 0.0,
    "meanResTime" : 442.77777777777777,
    "medianResTime" : 442.0,
    "minResTime" : 441.0,
    "maxResTime" : 447.0,
    "pct1ResTime" : 447.0,
    "pct2ResTime" : 447.0,
    "pct3ResTime" : 447.0,
    "throughput" : 0.04483813433505047,
    "receivedKBytesPerSec" : 0.01208527839499407,
    "sentKBytesPerSec" : 0.025703110209643186
  },
  "https://demoqa.com/BookStore/v1/Books?UserId=e4f64d0c-3f30-4f28-9b57-3587266a087e" : {
    "transaction" : "https://demoqa.com/BookStore/v1/Books?UserId=e4f64d0c-3f30-4f28-9b57-3587266a087e",
    "sampleCount" : 1,
    "errorCount" : 0,
    "errorPct" : 0.0,
    "meanResTime" : 247.0,
    "medianResTime" : 247.0,
    "minResTime" : 247.0,
    "maxResTime" : 247.0,
    "pct1ResTime" : 247.0,
    "pct2ResTime" : 247.0,
    "pct3ResTime" : 247.0,
    "throughput" : 4.048582995951417,
    "receivedKBytesPerSec" : 0.7314334514170041,
    "sentKBytesPerSec" : 2.791308198380567
  },
  "https://demoqa.com/Account/v1/User/6d10803b-2153-4c4b-87f2-567147cdacd9" : {
    "transaction" : "https://demoqa.com/Account/v1/User/6d10803b-2153-4c4b-87f2-567147cdacd9",
    "sampleCount" : 3,
    "errorCount" : 0,
    "errorPct" : 0.0,
    "meanResTime" : 260.6666666666667,
    "medianResTime" : 181.0,
    "minResTime" : 177.0,
    "maxResTime" : 424.0,
    "pct1ResTime" : 424.0,
    "pct2ResTime" : 424.0,
    "pct3ResTime" : 424.0,
    "throughput" : 0.024443303756935784,
    "receivedKBytesPerSec" : 0.028891157533018828,
    "sentKBytesPerSec" : 0.015674905078503745
  },
  "https://demoqa.com/BookStore/v1/Book?ISBN=9781491950296" : {
    "transaction" : "https://demoqa.com/BookStore/v1/Book?ISBN=9781491950296",
    "sampleCount" : 12,
    "errorCount" : 0,
    "errorPct" : 0.0,
    "meanResTime" : 225.41666666666669,
    "medianResTime" : 152.0,
    "minResTime" : 151.0,
    "maxResTime" : 448.0,
    "pct1ResTime" : 447.1,
    "pct2ResTime" : 448.0,
    "pct3ResTime" : 448.0,
    "throughput" : 0.05578359683335115,
    "receivedKBytesPerSec" : 0.0462502672964015,
    "sentKBytesPerSec" : 0.019829325436855293
  },
  "https://demoqa.com/Account/v1/User/47c8c972-c3e9-476a-8b1c-a8fa85940b7e" : {
    "transaction" : "https://demoqa.com/Account/v1/User/47c8c972-c3e9-476a-8b1c-a8fa85940b7e",
    "sampleCount" : 3,
    "errorCount" : 0,
    "errorPct" : 0.0,
    "meanResTime" : 207.0,
    "medianResTime" : 194.0,
    "minResTime" : 175.0,
    "maxResTime" : 252.0,
    "pct1ResTime" : 252.0,
    "pct2ResTime" : 252.0,
    "pct3ResTime" : 252.0,
    "throughput" : 0.04339524388127061,
    "receivedKBytesPerSec" : 0.02750343093646936,
    "sentKBytesPerSec" : 0.027828330223340855
  },
  "https://demoqa.com/BookStore/v1/Books?UserId=e87217b5-37cf-4a00-b253-fc928bb32e5e" : {
    "transaction" : "https://demoqa.com/BookStore/v1/Books?UserId=e87217b5-37cf-4a00-b253-fc928bb32e5e",
    "sampleCount" : 1,
    "errorCount" : 0,
    "errorPct" : 0.0,
    "meanResTime" : 249.0,
    "medianResTime" : 249.0,
    "minResTime" : 249.0,
    "maxResTime" : 249.0,
    "pct1ResTime" : 249.0,
    "pct2ResTime" : 249.0,
    "pct3ResTime" : 249.0,
    "throughput" : 4.016064257028112,
    "receivedKBytesPerSec" : 0.725558483935743,
    "sentKBytesPerSec" : 2.7688880522088355
  },
  "https://demoqa.com/Account/v1/User/7702ba96-0a49-4062-b5a2-bcdd30151f90" : {
    "transaction" : "https://demoqa.com/Account/v1/User/7702ba96-0a49-4062-b5a2-bcdd30151f90",
    "sampleCount" : 1,
    "errorCount" : 0,
    "errorPct" : 0.0,
    "meanResTime" : 182.0,
    "medianResTime" : 182.0,
    "minResTime" : 182.0,
    "maxResTime" : 182.0,
    "pct1ResTime" : 182.0,
    "pct2ResTime" : 182.0,
    "pct3ResTime" : 182.0,
    "throughput" : 5.4945054945054945,
    "receivedKBytesPerSec" : 1.7545930631868132,
    "sentKBytesPerSec" : 3.2784598214285716
  },
  "https://demoqa.com/Account/v1/User/11482878-8094-49f3-9232-a159276abe53" : {
    "transaction" : "https://demoqa.com/Account/v1/User/11482878-8094-49f3-9232-a159276abe53",
    "sampleCount" : 3,
    "errorCount" : 0,
    "errorPct" : 0.0,
    "meanResTime" : 200.0,
    "medianResTime" : 182.0,
    "minResTime" : 173.0,
    "maxResTime" : 245.0,
    "pct1ResTime" : 245.0,
    "pct2ResTime" : 245.0,
    "pct3ResTime" : 245.0,
    "throughput" : 0.04289022960569582,
    "receivedKBytesPerSec" : 0.027574284984130615,
    "sentKBytesPerSec" : 0.027504476667715095
  },
  "https://demoqa.com/BookStore/v1/Book?ISBN=9781449325862" : {
    "transaction" : "https://demoqa.com/BookStore/v1/Book?ISBN=9781449325862",
    "sampleCount" : 16,
    "errorCount" : 0,
    "errorPct" : 0.0,
    "meanResTime" : 170.18750000000003,
    "medianResTime" : 151.5,
    "minResTime" : 149.0,
    "maxResTime" : 449.0,
    "pct1ResTime" : 242.50000000000023,
    "pct2ResTime" : 449.0,
    "pct3ResTime" : 449.0,
    "throughput" : 0.08496221836352147,
    "receivedKBytesPerSec" : 0.06596187851464802,
    "sentKBytesPerSec" : 0.030201413558908024
  },
  "https://demoqa.com/books?book=9781449365035-10" : {
    "transaction" : "https://demoqa.com/books?book=9781449365035-10",
    "sampleCount" : 18,
    "errorCount" : 0,
    "errorPct" : 0.0,
    "meanResTime" : 490.6666666666667,
    "medianResTime" : 441.5,
    "minResTime" : 440.0,
    "maxResTime" : 1323.0,
    "pct1ResTime" : 535.5000000000013,
    "pct2ResTime" : 1323.0,
    "pct3ResTime" : 1323.0,
    "throughput" : 0.13691128148959475,
    "receivedKBytesPerSec" : 5.924837192044693,
    "sentKBytesPerSec" : 0.07782966620268954
  },
  "https://demoqa.com/BookStore/v1/Books?UserId=8e6477c4-07e6-41e4-952a-46ac16081c2f" : {
    "transaction" : "https://demoqa.com/BookStore/v1/Books?UserId=8e6477c4-07e6-41e4-952a-46ac16081c2f",
    "sampleCount" : 1,
    "errorCount" : 0,
    "errorPct" : 0.0,
    "meanResTime" : 176.0,
    "medianResTime" : 176.0,
    "minResTime" : 176.0,
    "maxResTime" : 176.0,
    "pct1ResTime" : 176.0,
    "pct2ResTime" : 176.0,
    "pct3ResTime" : 176.0,
    "throughput" : 5.681818181818182,
    "receivedKBytesPerSec" : 1.0265003551136365,
    "sentKBytesPerSec" : 3.9173473011363638
  },
  "https://demoqa.com/BookStore/v1/Books?UserId=923c78ab-706b-4723-bf5a-4067fa08e16f" : {
    "transaction" : "https://demoqa.com/BookStore/v1/Books?UserId=923c78ab-706b-4723-bf5a-4067fa08e16f",
    "sampleCount" : 1,
    "errorCount" : 0,
    "errorPct" : 0.0,
    "meanResTime" : 176.0,
    "medianResTime" : 176.0,
    "minResTime" : 176.0,
    "maxResTime" : 176.0,
    "pct1ResTime" : 176.0,
    "pct2ResTime" : 176.0,
    "pct3ResTime" : 176.0,
    "throughput" : 5.681818181818182,
    "receivedKBytesPerSec" : 1.0265003551136365,
    "sentKBytesPerSec" : 3.9173473011363638
  },
  "https://demoqa.com/books?book=9781449365035-8" : {
    "transaction" : "https://demoqa.com/books?book=9781449365035-8",
    "sampleCount" : 18,
    "errorCount" : 0,
    "errorPct" : 0.0,
    "meanResTime" : 458.77777777777777,
    "medianResTime" : 442.5,
    "minResTime" : 440.0,
    "maxResTime" : 736.0,
    "pct1ResTime" : 475.90000000000043,
    "pct2ResTime" : 736.0,
    "pct3ResTime" : 736.0,
    "throughput" : 0.13692586225258258,
    "receivedKBytesPerSec" : 0.4438353171735459,
    "sentKBytesPerSec" : 0.07757795027689453
  },
  "https://demoqa.com/books?book=9781449365035-9" : {
    "transaction" : "https://demoqa.com/books?book=9781449365035-9",
    "sampleCount" : 18,
    "errorCount" : 0,
    "errorPct" : 0.0,
    "meanResTime" : 32.55555555555556,
    "medianResTime" : 28.5,
    "minResTime" : 23.0,
    "maxResTime" : 54.0,
    "pct1ResTime" : 51.300000000000004,
    "pct2ResTime" : 54.0,
    "pct3ResTime" : 54.0,
    "throughput" : 0.13734272350620713,
    "receivedKBytesPerSec" : 0.20842831282094323,
    "sentKBytesPerSec" : 0.07349981687636865
  },
  "Total" : {
    "transaction" : "Total",
    "sampleCount" : 2440,
    "errorCount" : 18,
    "errorPct" : 0.73770493,
    "meanResTime" : 292.3733606557381,
    "medianResTime" : 150.0,
    "minResTime" : 5.0,
    "maxResTime" : 2394.0,
    "pct1ResTime" : 733.9000000000001,
    "pct2ResTime" : 1322.0,
    "pct3ResTime" : 1973.5900000000001,
    "throughput" : 9.573094895264848,
    "receivedKBytesPerSec" : 1025.2502408599503,
    "sentKBytesPerSec" : 8.551397974692112
  },
  "https://demoqa.com/books?book=9781449365035-4" : {
    "transaction" : "https://demoqa.com/books?book=9781449365035-4",
    "sampleCount" : 18,
    "errorCount" : 0,
    "errorPct" : 0.0,
    "meanResTime" : 83.72222222222223,
    "medianResTime" : 84.5,
    "minResTime" : 52.0,
    "maxResTime" : 136.0,
    "pct1ResTime" : 123.40000000000002,
    "pct2ResTime" : 136.0,
    "pct3ResTime" : 136.0,
    "throughput" : 0.13732281542287797,
    "receivedKBytesPerSec" : 19.743417921962497,
    "sentKBytesPerSec" : 0.08021672925662582
  },
  "https://demoqa.com/books?book=9781449365035-5" : {
    "transaction" : "https://demoqa.com/books?book=9781449365035-5",
    "sampleCount" : 18,
    "errorCount" : 0,
    "errorPct" : 0.0,
    "meanResTime" : 39.72222222222222,
    "medianResTime" : 39.0,
    "minResTime" : 21.0,
    "maxResTime" : 77.0,
    "pct1ResTime" : 74.30000000000001,
    "pct2ResTime" : 77.0,
    "pct3ResTime" : 77.0,
    "throughput" : 0.1373532037634778,
    "receivedKBytesPerSec" : 0.6816614753832536,
    "sentKBytesPerSec" : 0.0793104463788354
  },
  "https://demoqa.com/books?book=9781449365035-6" : {
    "transaction" : "https://demoqa.com/books?book=9781449365035-6",
    "sampleCount" : 18,
    "errorCount" : 0,
    "errorPct" : 0.0,
    "meanResTime" : 39.666666666666664,
    "medianResTime" : 14.5,
    "minResTime" : 9.0,
    "maxResTime" : 360.0,
    "pct1ResTime" : 81.90000000000043,
    "pct2ResTime" : 360.0,
    "pct3ResTime" : 360.0,
    "throughput" : 0.13736263736263737,
    "receivedKBytesPerSec" : 0.08920522836538462,
    "sentKBytesPerSec" : 0.07917429792429793
  },
  "https://demoqa.com/books?book=9781449365035-7" : {
    "transaction" : "https://demoqa.com/books?book=9781449365035-7",
    "sampleCount" : 18,
    "errorCount" : 0,
    "errorPct" : 0.0,
    "meanResTime" : 426.55555555555554,
    "medianResTime" : 443.0,
    "minResTime" : 148.0,
    "maxResTime" : 446.0,
    "pct1ResTime" : 445.1,
    "pct2ResTime" : 446.0,
    "pct3ResTime" : 446.0,
    "throughput" : 0.1369248206665196,
    "receivedKBytesPerSec" : 0.03955011638609757,
    "sentKBytesPerSec" : 0.07785222008382842
  },
  "https://demoqa.com/books?book=9781449365035-0" : {
    "transaction" : "https://demoqa.com/books?book=9781449365035-0",
    "sampleCount" : 18,
    "errorCount" : 0,
    "errorPct" : 0.0,
    "meanResTime" : 165.94444444444443,
    "medianResTime" : 150.0,
    "minResTime" : 149.0,
    "maxResTime" : 442.0,
    "pct1ResTime" : 180.10000000000042,
    "pct2ResTime" : 442.0,
    "pct3ResTime" : 442.0,
    "throughput" : 0.13721813108905456,
    "receivedKBytesPerSec" : 0.46043115080272606,
    "sentKBytesPerSec" : 0.0688770697068106
  },
  "https://demoqa.com/books?book=9781449365035-1" : {
    "transaction" : "https://demoqa.com/books?book=9781449365035-1",
    "sampleCount" : 18,
    "errorCount" : 1,
    "errorPct" : 5.5555553,
    "meanResTime" : 73.6111111111111,
    "medianResTime" : 21.5,
    "minResTime" : 6.0,
    "maxResTime" : 931.0,
    "pct1ResTime" : 139.00000000000125,
    "pct2ResTime" : 931.0,
    "pct3ResTime" : 931.0,
    "throughput" : 0.13736997550235436,
    "receivedKBytesPerSec" : 0.7261186709645663,
    "sentKBytesPerSec" : 0.07339515618203049
  },
  "https://demoqa.com/books?book=9781449365035-2" : {
    "transaction" : "https://demoqa.com/books?book=9781449365035-2",
    "sampleCount" : 18,
    "errorCount" : 1,
    "errorPct" : 5.5555553,
    "meanResTime" : 70.77777777777777,
    "medianResTime" : 19.5,
    "minResTime" : 5.0,
    "maxResTime" : 931.0,
    "pct1ResTime" : 137.20000000000124,
    "pct2ResTime" : 931.0,
    "pct3ResTime" : 931.0,
    "throughput" : 0.13737207225771,
    "receivedKBytesPerSec" : 1.9476098451893062,
    "sentKBytesPerSec" : 0.07428317297051842
  },
  "https://demoqa.com/books?book=9781449365035-3" : {
    "transaction" : "https://demoqa.com/books?book=9781449365035-3",
    "sampleCount" : 18,
    "errorCount" : 0,
    "errorPct" : 0.0,
    "meanResTime" : 23.55555555555556,
    "medianResTime" : 15.5,
    "minResTime" : 9.0,
    "maxResTime" : 61.0,
    "pct1ResTime" : 52.000000000000014,
    "pct2ResTime" : 61.0,
    "pct3ResTime" : 61.0,
    "throughput" : 0.1373542518771748,
    "receivedKBytesPerSec" : 2.4921167363294363,
    "sentKBytesPerSec" : 0.08035432389277211
  }
}